[{"Id":"1", "Title":"Rearranging Letters", "Description":""},{"Id":"2", "Title":"Matching Letter Shape", "Description":""},{"Id":"3", "Title":"Break It Up", "Description":""},{"Id":"4", "Title":"Memory Match", "Description":""},{"Id":"5", "Title":"Word Builder", "Description":""},{"Id":"6", "Title":"Alphabetize", "Description":""},{"Id":"7", "Title":"Classification", "Description":""},{"Id":"8", "Title":"Listen and Locate", "Description":""},{"Id":"9", "Title":"Fill in the Gaps", "Description":""},{"Id":"10", "Title":"Definitions", "Description":""}]