[{"Id":"and", "Kind":"Preposition", "Category":"Addition", "Form":"", "Article":"", "LinkedWord":"", "SunMoon":"", "Arabic":"و", "Symbols":"", "Drawing":"", "Letters":"", "Transliteration":"", "Difficulty":"", "Notes":""},{"Id":"bear", "Kind":"Noun", "Category":"Animal", "Form":"", "Article":"", "LinkedWord":"", "SunMoon":"", "Arabic":"دب", "Symbols":"", "Drawing":"49", "Letters":"د ب", "Transliteration":"dub", "Difficulty":"1", "Notes":""},{"Id":"bird", "Kind":"Noun", "Category":"Animal", "Form":"", "Article":"", "LinkedWord":"", "SunMoon":"", "Arabic":"عصفور", "Symbols":"", "Drawing":"4D", "Letters":"عـ ـصـ ـفـ ـو ر", "Transliteration":"asfuur ", "Difficulty":"", "Notes":""},{"Id":"camel", "Kind":"Noun", "Category":"Animal", "Form":"", "Article":"", "LinkedWord":"", "SunMoon":"", "Arabic":"جملٍ", "Symbols":"lam_kasrah_tanwin", "Drawing":"56", "Letters":"", "Transliteration":"", "Difficulty":"", "Notes":""},{"Id":"cat", "Kind":"Noun", "Category":"Animal", "Form":"", "Article":"", "LinkedWord":"", "SunMoon":"", "Arabic":"هر", "Symbols":"", "Drawing":"59", "Letters":"هـ ـر", "Transliteration":"hir", "Difficulty":"1", "Notes":""},{"Id":"deer", "Kind":"Noun", "Category":"Animal", "Form":"", "Article":"", "LinkedWord":"", "SunMoon":"", "Arabic":"غزال", "Symbols":"", "Drawing":"69", "Letters":"", "Transliteration":"", "Difficulty":"", "Notes":""},{"Id":"dog", "Kind":"Noun", "Category":"Animal", "Form":"", "Article":"", "LinkedWord":"", "SunMoon":"", "Arabic":"كلب", "Symbols":"", "Drawing":"6B", "Letters":"كـ ـلـ ـب", "Transliteration":"kalb", "Difficulty":"1", "Notes":""},{"Id":"duck", "Kind":"Noun", "Category":"Animal", "Form":"", "Article":"", "LinkedWord":"", "SunMoon":"", "Arabic":"بط", "Symbols":"", "Drawing":"31", "Letters":"", "Transliteration":"", "Difficulty":"", "Notes":""},{"Id":"eagle", "Kind":"Noun", "Category":"Animal", "Form":"", "Article":"", "LinkedWord":"", "SunMoon":"", "Arabic":"نسر", "Symbols":"", "Drawing":"6D", "Letters":"نـ ـسـ ـر", "Transliteration":"neser", "Difficulty":"", "Notes":""},{"Id":"elephant", "Kind":"Noun", "Category":"Animal", "Form":"", "Article":"", "LinkedWord":"", "SunMoon":"", "Arabic":"فيل", "Symbols":"", "Drawing":"6F", "Letters":"", "Transliteration":"", "Difficulty":"", "Notes":""},{"Id":"lion", "Kind":"Noun", "Category":"Animal", "Form":"", "Article":"", "LinkedWord":"", "SunMoon":"", "Arabic":"أسد", "Symbols":"", "Drawing":"D1", "Letters":"أ سـ ـد", "Transliteration":"asad", "Difficulty":"", "Notes":""},{"Id":"lion_dual", "Kind":"Noun", "Category":"Animal", "Form":"Dual", "Article":"", "LinkedWord":"", "SunMoon":"", "Arabic":"أسدان", "Symbols":"", "Drawing":"2039", "Letters":"", "Transliteration":"", "Difficulty":"", "Notes":""},{"Id":"lion_plural", "Kind":"Noun", "Category":"Animal", "Form":"Plural", "Article":"", "LinkedWord":"", "SunMoon":"", "Arabic":"أسودٌ", "Symbols":"dal_dammah_tanwin", "Drawing":"203A", "Letters":"", "Transliteration":"", "Difficulty":"", "Notes":""},{"Id":"mouse", "Kind":"Noun", "Category":"Animal", "Form":"", "Article":"", "LinkedWord":"", "SunMoon":"", "Arabic":"فأر", "Symbols":"", "Drawing":"D8", "Letters":"فـ ـا ر", "Transliteration":"far", "Difficulty":"1", "Notes":""},{"Id":"parrot", "Kind":"Noun", "Category":"Animal", "Form":"", "Article":"", "LinkedWord":"", "SunMoon":"", "Arabic":"ببغاء", "Symbols":"hamza", "Drawing":"E2", "Letters":"", "Transliteration":"", "Difficulty":"", "Notes":""},{"Id":"the_bear", "Kind":"Noun", "Category":"Animal", "Form":"", "Article":"Determinative", "LinkedWord":"bear", "SunMoon":"", "Arabic":"الدب", "Symbols":"", "Drawing":"49", "Letters":"", "Transliteration":"", "Difficulty":"", "Notes":"sun"},{"Id":"the_whale", "Kind":"Noun", "Category":"Animal", "Form":"", "Article":"Determinative", "LinkedWord":"whale", "SunMoon":"", "Arabic":"الحوت", "Symbols":"", "Drawing":"FD", "Letters":"", "Transliteration":"", "Difficulty":"", "Notes":"moon"},{"Id":"the_wolf", "Kind":"Noun", "Category":"Animal", "Form":"", "Article":"Determinative", "LinkedWord":"wolf", "SunMoon":"", "Arabic":"الذئب", "Symbols":"", "Drawing":"FF", "Letters":"", "Transliteration":"", "Difficulty":"", "Notes":"sun"},{"Id":"tiger", "Kind":"Noun", "Category":"Animal", "Form":"", "Article":"", "LinkedWord":"", "SunMoon":"", "Arabic":"نمر", "Symbols":"", "Drawing":"F5", "Letters":"نـ ـمـ ـر", "Transliteration":"nemer", "Difficulty":"", "Notes":""},{"Id":"whale", "Kind":"Noun", "Category":"Animal", "Form":"", "Article":"", "LinkedWord":"", "SunMoon":"", "Arabic":"حوت", "Symbols":"", "Drawing":"FD", "Letters":"حـ ـو ت", "Transliteration":"huut", "Difficulty":"", "Notes":""},{"Id":"wolf", "Kind":"Noun", "Category":"Animal", "Form":"", "Article":"", "LinkedWord":"", "SunMoon":"", "Arabic":"ذئب", "Symbols":"alef_maqsura_hamza", "Drawing":"FF", "Letters":"", "Transliteration":"", "Difficulty":"", "Notes":""},{"Id":"back", "Kind":"Noun", "Category":"BodyPart", "Form":"", "Article":"", "LinkedWord":"", "SunMoon":"", "Arabic":"ظهر", "Symbols":"", "Drawing":"45", "Letters":"ظـ ـهـ ـر", "Transliteration":"DHahr", "Difficulty":"", "Notes":""},{"Id":"belly", "Kind":"Noun", "Category":"BodyPart", "Form":"", "Article":"", "LinkedWord":"", "SunMoon":"", "Arabic":"بطن", "Symbols":"", "Drawing":"4B", "Letters":"بـ ـطـ ـن", "Transliteration":"batn", "Difficulty":"1", "Notes":""},{"Id":"brain", "Kind":"Noun", "Category":"BodyPart", "Form":"", "Article":"", "LinkedWord":"", "SunMoon":"", "Arabic":"دماغ", "Symbols":"", "Drawing":"52", "Letters":"", "Transliteration":"", "Difficulty":"", "Notes":""},{"Id":"chest", "Kind":"Noun", "Category":"BodyPart", "Form":"", "Article":"", "LinkedWord":"", "SunMoon":"", "Arabic":"صدر", "Symbols":"", "Drawing":"63", "Letters":"صـ ـد ر", "Transliteration":"Sadr", "Difficulty":"", "Notes":""},{"Id":"ear", "Kind":"Noun", "Category":"BodyPart", "Form":"", "Article":"", "LinkedWord":"", "SunMoon":"", "Arabic":"أذن", "Symbols":"", "Drawing":"6E", "Letters":"ا د ن", "Transliteration":"Eden", "Difficulty":"1", "Notes":""},{"Id":"eye", "Kind":"Noun", "Category":"BodyPart", "Form":"", "Article":"", "LinkedWord":"", "SunMoon":"", "Arabic":"عين", "Symbols":"", "Drawing":"70", "Letters":"عـ ـيـ ـن", "Transliteration":"ain", "Difficulty":"1", "Notes":""},{"Id":"face", "Kind":"Noun", "Category":"BodyPart", "Form":"", "Article":"", "LinkedWord":"", "SunMoon":"", "Arabic":"وجه", "Symbols":"", "Drawing":"71", "Letters":"و جـ ـه", "Transliteration":"wajeh", "Difficulty":"", "Notes":""},{"Id":"finger", "Kind":"Noun", "Category":"BodyPart", "Form":"", "Article":"", "LinkedWord":"", "SunMoon":"", "Arabic":"إصبع", "Symbols":"alef_hamza_low", "Drawing":"75", "Letters":"", "Transliteration":"", "Difficulty":"", "Notes":""},{"Id":"foot", "Kind":"Noun", "Category":"BodyPart", "Form":"", "Article":"", "LinkedWord":"", "SunMoon":"", "Arabic":"قدم", "Symbols":"", "Drawing":"CC", "Letters":"ر جـ ـل", "Transliteration":"rijl", "Difficulty":"1", "Notes":""},{"Id":"hair", "Kind":"Noun", "Category":"BodyPart", "Form":"", "Article":"", "LinkedWord":"", "SunMoon":"", "Arabic":"شعر", "Symbols":"", "Drawing":"C7", "Letters":"شـ ـعـ ـر", "Transliteration":"sha’ar", "Difficulty":"", "Notes":""},{"Id":"hand", "Kind":"Noun", "Category":"BodyPart", "Form":"", "Article":"", "LinkedWord":"", "SunMoon":"", "Arabic":"يد", "Symbols":"", "Drawing":"D0", "Letters":"يـ ـد", "Transliteration":"yad", "Difficulty":"1", "Notes":""},{"Id":"head", "Kind":"Noun", "Category":"BodyPart", "Form":"", "Article":"", "LinkedWord":"", "SunMoon":"", "Arabic":"رأس", "Symbols":"", "Drawing":"CA", "Letters":"ر ا س", "Transliteration":"ras", "Difficulty":"1", "Notes":""},{"Id":"leg", "Kind":"Noun", "Category":"BodyPart", "Form":"", "Article":"", "LinkedWord":"", "SunMoon":"", "Arabic":"رِجل", "Symbols":"reh_kasrah", "Drawing":"CF", "Letters":"", "Transliteration":"", "Difficulty":"", "Notes":""},{"Id":"lips", "Kind":"Noun", "Category":"BodyPart", "Form":"", "Article":"", "LinkedWord":"", "SunMoon":"", "Arabic":"شفاه", "Symbols":"", "Drawing":"2022", "Letters":"", "Transliteration":"", "Difficulty":"", "Notes":""},{"Id":"mouth", "Kind":"Noun", "Category":"BodyPart", "Form":"", "Article":"", "LinkedWord":"", "SunMoon":"", "Arabic":"فم", "Symbols":"", "Drawing":"D5", "Letters":"فـ ـم", "Transliteration":"fam", "Difficulty":"1", "Notes":""},{"Id":"nail", "Kind":"Noun", "Category":"BodyPart", "Form":"", "Article":"", "LinkedWord":"", "SunMoon":"", "Arabic":"ظفر", "Symbols":"", "Drawing":"152", "Letters":"", "Transliteration":"", "Difficulty":"", "Notes":""},{"Id":"nose", "Kind":"Noun", "Category":"BodyPart", "Form":"", "Article":"", "LinkedWord":"", "SunMoon":"", "Arabic":"أنف", "Symbols":"", "Drawing":"DB", "Letters":"أ نـ ـف", "Transliteration":"anf", "Difficulty":"1", "Notes":""},{"Id":"the_back", "Kind":"Noun", "Category":"BodyPart", "Form":"", "Article":"Determinative", "LinkedWord":"back", "SunMoon":"", "Arabic":"الظهر", "Symbols":"", "Drawing":"45", "Letters":"", "Transliteration":"", "Difficulty":"", "Notes":""},{"Id":"the_eye", "Kind":"Noun", "Category":"BodyPart", "Form":"", "Article":"Determinative", "LinkedWord":"eye", "SunMoon":"", "Arabic":"العين", "Symbols":"", "Drawing":"70", "Letters":"", "Transliteration":"", "Difficulty":"", "Notes":"moon"},{"Id":"the_leg", "Kind":"Noun", "Category":"BodyPart", "Form":"", "Article":"Determinative", "LinkedWord":"leg", "SunMoon":"", "Arabic":"الرجل", "Symbols":"", "Drawing":"CF", "Letters":"", "Transliteration":"", "Difficulty":"", "Notes":"sun"},{"Id":"the_tooth", "Kind":"Noun", "Category":"BodyPart", "Form":"", "Article":"Determinative", "LinkedWord":"tooth", "SunMoon":"", "Arabic":"السن", "Symbols":"", "Drawing":"DF", "Letters":"", "Transliteration":"", "Difficulty":"", "Notes":"sun"},{"Id":"tongue", "Kind":"Noun", "Category":"BodyPart", "Form":"", "Article":"", "LinkedWord":"", "SunMoon":"", "Arabic":"لسان", "Symbols":"", "Drawing":"", "Letters":"لـ ـسـ ـا ن", "Transliteration":"lisan", "Difficulty":"", "Notes":""},{"Id":"tooth", "Kind":"Noun", "Category":"BodyPart", "Form":"", "Article":"", "LinkedWord":"", "SunMoon":"", "Arabic":"سن", "Symbols":"", "Drawing":"DF", "Letters":"سـ ـن", "Transliteration":"sin", "Difficulty":"1", "Notes":""},{"Id":"coat", "Kind":"Noun", "Category":"Clothes", "Form":"", "Article":"", "LinkedWord":"", "SunMoon":"", "Arabic":"معطف", "Symbols":"", "Drawing":"", "Letters":"", "Transliteration":"", "Difficulty":"", "Notes":""},{"Id":"hat", "Kind":"Noun", "Category":"Clothes", "Form":"", "Article":"", "LinkedWord":"", "SunMoon":"", "Arabic":"قبعة", "Symbols":"", "Drawing":"C9", "Letters":"", "Transliteration":"", "Difficulty":"", "Notes":""},{"Id":"shirt", "Kind":"Noun", "Category":"Clothes", "Form":"", "Article":"", "LinkedWord":"", "SunMoon":"", "Arabic":"قميص", "Symbols":"", "Drawing":"ED", "Letters":"", "Transliteration":"", "Difficulty":"", "Notes":""},{"Id":"shoe", "Kind":"Noun", "Category":"Clothes", "Form":"", "Article":"", "LinkedWord":"", "SunMoon":"", "Arabic":"حذاء", "Symbols":"", "Drawing":"", "Letters":"", "Transliteration":"", "Difficulty":"", "Notes":""},{"Id":"the_coat", "Kind":"Noun", "Category":"Clothes", "Form":"", "Article":"Determinative", "LinkedWord":"coat", "SunMoon":"", "Arabic":"المعطف", "Symbols":"", "Drawing":"66", "Letters":"", "Transliteration":"", "Difficulty":"", "Notes":""},{"Id":"the_hat", "Kind":"Noun", "Category":"Clothes", "Form":"", "Article":"Determinative", "LinkedWord":"hat", "SunMoon":"", "Arabic":"القبعة", "Symbols":"", "Drawing":"C9", "Letters":"", "Transliteration":"", "Difficulty":"", "Notes":""},{"Id":"the_shirt", "Kind":"Noun", "Category":"Clothes", "Form":"", "Article":"Determinative", "LinkedWord":"shirt", "SunMoon":"", "Arabic":"القميص", "Symbols":"", "Drawing":"ED", "Letters":"", "Transliteration":"", "Difficulty":"", "Notes":""},{"Id":"the_shoe", "Kind":"Noun", "Category":"Clothes", "Form":"", "Article":"Determinative", "LinkedWord":"shoe", "SunMoon":"", "Arabic":"الحذاء", "Symbols":"", "Drawing":"23", "Letters":"", "Transliteration":"", "Difficulty":"", "Notes":""},{"Id":"the_trousers", "Kind":"Noun", "Category":"Clothes", "Form":"", "Article":"Determinative", "LinkedWord":"trousers", "SunMoon":"", "Arabic":"البنطال", "Symbols":"", "Drawing":"F8", "Letters":"", "Transliteration":"", "Difficulty":"", "Notes":""},{"Id":"trousers", "Kind":"Noun", "Category":"Clothes", "Form":"", "Article":"", "LinkedWord":"", "SunMoon":"", "Arabic":"بنطال", "Symbols":"", "Drawing":"F8", "Letters":"", "Transliteration":"", "Difficulty":"", "Notes":""},{"Id":"costume", "Kind":"Noun", "Category":"Clothes ", "Form":"", "Article":"", "LinkedWord":"", "SunMoon":"", "Arabic":"لِباساً", "Symbols":"lam_kasrah,alef_fathah_tanwin", "Drawing":"67", "Letters":"", "Transliteration":"", "Difficulty":"", "Notes":""},{"Id":"color_black", "Kind":"Adjective", "Category":"Color", "Form":"", "Article":"", "LinkedWord":"", "SunMoon":"", "Arabic":"أسود", "Symbols":"", "Drawing":"", "Letters":"", "Transliteration":"", "Difficulty":"", "Notes":""},{"Id":"color_blue", "Kind":"Adjective", "Category":"Color", "Form":"", "Article":"", "LinkedWord":"", "SunMoon":"", "Arabic":"أزرق", "Symbols":"", "Drawing":"", "Letters":"", "Transliteration":"", "Difficulty":"", "Notes":""},{"Id":"color_brown", "Kind":"Adjective", "Category":"Color", "Form":"", "Article":"", "LinkedWord":"", "SunMoon":"", "Arabic":"بُني", "Symbols":"beh_dammah", "Drawing":"", "Letters":"", "Transliteration":"", "Difficulty":"", "Notes":""},{"Id":"color_gold", "Kind":"Adjective", "Category":"Color", "Form":"", "Article":"", "LinkedWord":"", "SunMoon":"", "Arabic":"ذهبي", "Symbols":"", "Drawing":"", "Letters":"", "Transliteration":"", "Difficulty":"", "Notes":""},{"Id":"color_green", "Kind":"Adjective", "Category":"Color", "Form":"", "Article":"", "LinkedWord":"", "SunMoon":"", "Arabic":"أخضر", "Symbols":"", "Drawing":"", "Letters":"", "Transliteration":"", "Difficulty":"", "Notes":""},{"Id":"color_grey", "Kind":"Adjective", "Category":"Color", "Form":"", "Article":"", "LinkedWord":"", "SunMoon":"", "Arabic":"رمادي", "Symbols":"", "Drawing":"", "Letters":"", "Transliteration":"", "Difficulty":"", "Notes":""},{"Id":"color_orange", "Kind":"Adjective", "Category":"Color", "Form":"", "Article":"", "LinkedWord":"", "SunMoon":"", "Arabic":"برتقالي", "Symbols":"", "Drawing":"", "Letters":"", "Transliteration":"", "Difficulty":"", "Notes":""},{"Id":"color_pink", "Kind":"Adjective", "Category":"Color", "Form":"", "Article":"", "LinkedWord":"", "SunMoon":"", "Arabic":"وردي", "Symbols":"", "Drawing":"", "Letters":"", "Transliteration":"", "Difficulty":"", "Notes":""},{"Id":"color_purple", "Kind":"Adjective", "Category":"Color", "Form":"", "Article":"", "LinkedWord":"", "SunMoon":"", "Arabic":"بنفسجي", "Symbols":"", "Drawing":"", "Letters":"", "Transliteration":"", "Difficulty":"", "Notes":""},{"Id":"color_red", "Kind":"Adjective", "Category":"Color", "Form":"", "Article":"", "LinkedWord":"", "SunMoon":"", "Arabic":"أحمر", "Symbols":"", "Drawing":"", "Letters":"", "Transliteration":"", "Difficulty":"", "Notes":""},{"Id":"color_silver", "Kind":"Adjective", "Category":"Color", "Form":"", "Article":"", "LinkedWord":"", "SunMoon":"", "Arabic":"فضي", "Symbols":"", "Drawing":"", "Letters":"", "Transliteration":"", "Difficulty":"", "Notes":""},{"Id":"color_white", "Kind":"Adjective", "Category":"Color", "Form":"", "Article":"", "LinkedWord":"", "SunMoon":"", "Arabic":"أبيض", "Symbols":"", "Drawing":"", "Letters":"", "Transliteration":"", "Difficulty":"", "Notes":""},{"Id":"color_yellow", "Kind":"Adjective", "Category":"Color", "Form":"", "Article":"", "LinkedWord":"", "SunMoon":"", "Arabic":"أصفر", "Symbols":"", "Drawing":"", "Letters":"", "Transliteration":"", "Difficulty":"", "Notes":""},{"Id":"from", "Kind":"Preposition", "Category":"Direction", "Form":"", "Article":"", "LinkedWord":"", "SunMoon":"", "Arabic":"من", "Symbols":"", "Drawing":"", "Letters":"", "Transliteration":"", "Difficulty":"", "Notes":""},{"Id":"to", "Kind":"Preposition", "Category":"Direction", "Form":"", "Article":"", "LinkedWord":"", "SunMoon":"", "Arabic":"إلى", "Symbols":"alef_hamza_low, alef_maqsura", "Drawing":"", "Letters":"", "Transliteration":"", "Difficulty":"", "Notes":""},{"Id":"aunt_father", "Kind":"Noun", "Category":"FamilyMember", "Form":"", "Article":"", "LinkedWord":"", "SunMoon":"", "Arabic":"عمة", "Symbols":"", "Drawing":"A1", "Letters":"عـ ـمـ ـة", "Transliteration":"amma", "Difficulty":"1", "Notes":""},{"Id":"aunt_mother", "Kind":"Noun", "Category":"FamilyMember", "Form":"", "Article":"", "LinkedWord":"", "SunMoon":"", "Arabic":"خالة", "Symbols":"", "Drawing":"3B", "Letters":"خـ ا لـ ـة", "Transliteration":"khala", "Difficulty":"2", "Notes":""},{"Id":"boy", "Kind":"Noun", "Category":"FamilyMember", "Form":"", "Article":"", "LinkedWord":"", "SunMoon":"", "Arabic":"صبي", "Symbols":"", "Drawing":"51", "Letters":"صـ ـبـ ـي", "Transliteration":"Sabi", "Difficulty":"", "Notes":""},{"Id":"brother", "Kind":"Noun", "Category":"FamilyMember", "Form":"", "Article":"", "LinkedWord":"", "SunMoon":"", "Arabic":"أخ", "Symbols":"", "Drawing":"2F", "Letters":"أ خ", "Transliteration":"akh", "Difficulty":"1", "Notes":""},{"Id":"father", "Kind":"Noun", "Category":"FamilyMember", "Form":"", "Article":"", "LinkedWord":"", "SunMoon":"", "Arabic":"بابا", "Symbols":"", "Drawing":"5B", "Letters":"بـ ا بـ ا", "Transliteration":"baba", "Difficulty":"1", "Notes":""},{"Id":"girl", "Kind":"Noun", "Category":"FamilyMember", "Form":"", "Article":"", "LinkedWord":"", "SunMoon":"", "Arabic":"بنت", "Symbols":"", "Drawing":"C0", "Letters":"بـ ـنـ ـت", "Transliteration":"bint", "Difficulty":"", "Notes":""},{"Id":"granddaughter", "Kind":"Noun", "Category":"FamilyMember", "Form":"", "Article":"", "LinkedWord":"", "SunMoon":"", "Arabic":"حفيدة", "Symbols":"", "Drawing":"33", "Letters":"حـ ـفـ ـيـ ـد ة", "Transliteration":"hafida", "Difficulty":"", "Notes":""},{"Id":"grandfather", "Kind":"Noun", "Category":"FamilyMember", "Form":"", "Article":"", "LinkedWord":"", "SunMoon":"", "Arabic":"جد", "Symbols":"", "Drawing":"34", "Letters":"جـ ـد ", "Transliteration":"jadd", "Difficulty":"1", "Notes":""},{"Id":"grandmother", "Kind":"Noun", "Category":"FamilyMember", "Form":"", "Article":"", "LinkedWord":"", "SunMoon":"", "Arabic":"جدة", "Symbols":"", "Drawing":"35", "Letters":"ج د ة", "Transliteration":"jadda", "Difficulty":"1", "Notes":""},{"Id":"grandson", "Kind":"Noun", "Category":"FamilyMember", "Form":"", "Article":"", "LinkedWord":"", "SunMoon":"", "Arabic":"حفيد", "Symbols":"", "Drawing":"36", "Letters":"حـ ـفـ ـيـ ـد", "Transliteration":"hafid", "Difficulty":"", "Notes":""},{"Id":"kid", "Kind":"Noun", "Category":"FamilyMember", "Form":"", "Article":"", "LinkedWord":"", "SunMoon":"", "Arabic":"ولد", "Symbols":"", "Drawing":"28", "Letters":"و لـ ـد", "Transliteration":"walad", "Difficulty":"", "Notes":""},{"Id":"man", "Kind":"Noun", "Category":"FamilyMember", "Form":"", "Article":"", "LinkedWord":"", "SunMoon":"", "Arabic":"رَجُلٍ", "Symbols":"reh_fathah,jeem_dammah,lam_kasrah_tanwin", "Drawing":"2D", "Letters":"ر جـ ـل", "Transliteration":"rajol", "Difficulty":"", "Notes":"double_diacritic"},{"Id":"mother", "Kind":"Noun", "Category":"FamilyMember", "Form":"", "Article":"", "LinkedWord":"", "SunMoon":"", "Arabic":"ماما", "Symbols":"", "Drawing":"D6", "Letters":"مـ ا مـ ا", "Transliteration":"mama", "Difficulty":"1", "Notes":""},{"Id":"sister", "Kind":"Noun", "Category":"FamilyMember", "Form":"", "Article":"", "LinkedWord":"", "SunMoon":"", "Arabic":"أخت", "Symbols":"", "Drawing":"EE", "Letters":"أ خـ ـت", "Transliteration":"ukht", "Difficulty":"1", "Notes":""},{"Id":"uncle_father", "Kind":"Noun", "Category":"FamilyMember", "Form":"", "Article":"", "LinkedWord":"", "SunMoon":"", "Arabic":"عم", "Symbols":"", "Drawing":"A4", "Letters":"عـ ـم", "Transliteration":"am", "Difficulty":"1", "Notes":""},{"Id":"uncle_mother", "Kind":"Noun", "Category":"FamilyMember", "Form":"", "Article":"", "LinkedWord":"", "SunMoon":"", "Arabic":"خال", "Symbols":"", "Drawing":"A2", "Letters":"خـ ا ل", "Transliteration":"khal", "Difficulty":"1", "Notes":""},{"Id":"woman", "Kind":"Noun", "Category":"FamilyMember", "Form":"", "Article":"", "LinkedWord":"", "SunMoon":"", "Arabic":"مرأة", "Symbols":"", "Drawing":"22", "Letters":"مـ ـر أ ة", "Transliteration":"mara", "Difficulty":"", "Notes":""},{"Id":"sad", "Kind":"Adjective", "Category":"Feeling", "Form":"", "Article":"", "LinkedWord":"", "SunMoon":"", "Arabic":"حزين", "Symbols":"", "Drawing":"", "Letters":"", "Transliteration":"", "Difficulty":"", "Notes":""},{"Id":"anger", "Kind":"Noun", "Category":"Feeling", "Form":"", "Article":"", "LinkedWord":"", "SunMoon":"", "Arabic":"غيظ", "Symbols":"", "Drawing":"41", "Letters":"غـ ـيـ ـظ", "Transliteration":"ghayDH", "Difficulty":"", "Notes":""},{"Id":"cold_food", "Kind":"Adjective", "Category":"Food", "Form":"", "Article":"", "LinkedWord":"", "SunMoon":"", "Arabic":"بارد", "Symbols":"", "Drawing":"", "Letters":"بـ ـا ر د", "Transliteration":"bared", "Difficulty":"", "Notes":""},{"Id":"delicious", "Kind":"Adjective", "Category":"Food", "Form":"", "Article":"", "LinkedWord":"", "SunMoon":"", "Arabic":"حلو", "Symbols":"", "Drawing":"", "Letters":"حـ ـلـ ـو", "Transliteration":"helu", "Difficulty":"1", "Notes":""},{"Id":"apple", "Kind":"Noun", "Category":"Food", "Form":"", "Article":"", "LinkedWord":"", "SunMoon":"", "Arabic":"تفاح", "Symbols":"", "Drawing":"42", "Letters":"تـ ـفـ ـا ح", "Transliteration":"tuffah", "Difficulty":"", "Notes":""},{"Id":"apricot", "Kind":"Noun", "Category":"Food", "Form":"", "Article":"", "LinkedWord":"", "SunMoon":"", "Arabic":"مشمش", "Symbols":"", "Drawing":"43", "Letters":"مـ ـشـ ـمـ ـش", "Transliteration":"mishmosh", "Difficulty":"2", "Notes":""},{"Id":"banana", "Kind":"Noun", "Category":"Food", "Form":"", "Article":"", "LinkedWord":"", "SunMoon":"", "Arabic":"موز", "Symbols":"", "Drawing":"46", "Letters":"مـ ـو ز", "Transliteration":"mawz", "Difficulty":"1", "Notes":""},{"Id":"berry", "Kind":"Noun", "Category":"Food", "Form":"", "Article":"", "LinkedWord":"", "SunMoon":"", "Arabic":"توت", "Symbols":"", "Drawing":"4C", "Letters":"تـ ـو ت", "Transliteration":"tuut", "Difficulty":"1", "Notes":""},{"Id":"bread", "Kind":"Noun", "Category":"Food", "Form":"", "Article":"", "LinkedWord":"", "SunMoon":"", "Arabic":"خبز", "Symbols":"", "Drawing":"53", "Letters":"خـ ـبـ ـز", "Transliteration":"khubz", "Difficulty":"1", "Notes":""},{"Id":"broad_bean", "Kind":"Noun", "Category":"Food", "Form":"", "Article":"", "LinkedWord":"", "SunMoon":"", "Arabic":"فول", "Symbols":"", "Drawing":"55", "Letters":"", "Transliteration":"", "Difficulty":"", "Notes":""},{"Id":"bulgar", "Kind":"Noun", "Category":"Food", "Form":"", "Article":"", "LinkedWord":"", "SunMoon":"", "Arabic":"برغل", "Symbols":"", "Drawing":"5F", "Letters":"", "Transliteration":"", "Difficulty":"", "Notes":""},{"Id":"carrot", "Kind":"Noun", "Category":"Food", "Form":"", "Article":"", "LinkedWord":"", "SunMoon":"", "Arabic":"جَزَر", "Symbols":"jeem_fathah,zain_fathah", "Drawing":"58", "Letters":"", "Transliteration":"", "Difficulty":"", "Notes":""},{"Id":"cheese", "Kind":"Noun", "Category":"Food", "Form":"", "Article":"", "LinkedWord":"", "SunMoon":"", "Arabic":"جبن", "Symbols":"", "Drawing":"61", "Letters":"جـ ـبـ ـن", "Transliteration":"jubn", "Difficulty":"1", "Notes":""},{"Id":"cherry", "Kind":"Noun", "Category":"Food", "Form":"", "Article":"", "LinkedWord":"", "SunMoon":"", "Arabic":"كرز", "Symbols":"", "Drawing":"62", "Letters":"كـ ـر ز", "Transliteration":"karaz", "Difficulty":"", "Notes":""},{"Id":"chickpea", "Kind":"Noun", "Category":"Food", "Form":"", "Article":"", "LinkedWord":"", "SunMoon":"", "Arabic":"حمص", "Symbols":"", "Drawing":"64", "Letters":"", "Transliteration":"", "Difficulty":"", "Notes":""},{"Id":"cucumber", "Kind":"Noun", "Category":"Food", "Form":"", "Article":"", "LinkedWord":"", "SunMoon":"", "Arabic":"خيار", "Symbols":"", "Drawing":"68", "Letters":"خـ ـيـ ـا ر", "Transliteration":"khiyar", "Difficulty":"", "Notes":""},{"Id":"fig", "Kind":"Noun", "Category":"Food", "Form":"", "Article":"", "LinkedWord":"", "SunMoon":"", "Arabic":"تين", "Symbols":"", "Drawing":"74", "Letters":"تـ ـيـ ـن", "Transliteration":"tiin", "Difficulty":"", "Notes":""},{"Id":"food", "Kind":"Noun", "Category":"Food", "Form":"", "Article":"", "LinkedWord":"", "SunMoon":"", "Arabic":"أكل", "Symbols":"", "Drawing":"5D", "Letters":"أ كـ ـل", "Transliteration":"akl", "Difficulty":"", "Notes":""},{"Id":"garlic", "Kind":"Noun", "Category":"Food", "Form":"", "Article":"", "LinkedWord":"", "SunMoon":"", "Arabic":"ثوم", "Symbols":"", "Drawing":"C4", "Letters":"ثـ ـو م", "Transliteration":"thuum", "Difficulty":"", "Notes":""},{"Id":"grapes", "Kind":"Noun", "Category":"Food", "Form":"", "Article":"", "LinkedWord":"", "SunMoon":"", "Arabic":"عنب", "Symbols":"", "Drawing":"C6", "Letters":"عـ ـنـ ـب", "Transliteration":"e’nab", "Difficulty":"", "Notes":""},{"Id":"icecream", "Kind":"Noun", "Category":"Food", "Form":"", "Article":"", "LinkedWord":"", "SunMoon":"", "Arabic":"بوظة", "Symbols":"", "Drawing":"CD", "Letters":"", "Transliteration":"", "Difficulty":"", "Notes":""},{"Id":"juice", "Kind":"Noun", "Category":"Food", "Form":"", "Article":"", "LinkedWord":"", "SunMoon":"", "Arabic":"عَصير", "Symbols":"ain_fathah", "Drawing":"39", "Letters":"", "Transliteration":"", "Difficulty":"", "Notes":""},{"Id":"meat", "Kind":"Noun", "Category":"Food", "Form":"", "Article":"", "LinkedWord":"", "SunMoon":"", "Arabic":"لحم", "Symbols":"", "Drawing":"D3", "Letters":"", "Transliteration":"", "Difficulty":"", "Notes":""},{"Id":"oil", "Kind":"Noun", "Category":"Food", "Form":"", "Article":"", "LinkedWord":"", "SunMoon":"", "Arabic":"زيت", "Symbols":"", "Drawing":"D9", "Letters":"ز يـ ـت", "Transliteration":"zayt", "Difficulty":"", "Notes":""},{"Id":"onion", "Kind":"Noun", "Category":"Food", "Form":"", "Article":"", "LinkedWord":"", "SunMoon":"", "Arabic":"بصل", "Symbols":"", "Drawing":"DD", "Letters":"بـ ـصـ ـل", "Transliteration":"baSal", "Difficulty":"", "Notes":""},{"Id":"pear", "Kind":"Noun", "Category":"Food", "Form":"", "Article":"", "LinkedWord":"", "SunMoon":"", "Arabic":"إنجاص", "Symbols":"", "Drawing":"E4", "Letters":"", "Transliteration":"", "Difficulty":"", "Notes":""},{"Id":"pear_big", "Kind":"Noun", "Category":"Food", "Form":"", "Article":"", "LinkedWord":"", "SunMoon":"", "Arabic":"كمثرى", "Symbols":"", "Drawing":"B6", "Letters":"", "Transliteration":"", "Difficulty":"", "Notes":"a different kind of pear"},{"Id":"plum", "Kind":"Noun", "Category":"Food", "Form":"", "Article":"", "LinkedWord":"", "SunMoon":"", "Arabic":"خوخ", "Symbols":"", "Drawing":"E3", "Letters":"خـ ـو خ", "Transliteration":"khawkh", "Difficulty":"", "Notes":""},{"Id":"potato", "Kind":"Noun", "Category":"Food", "Form":"", "Article":"", "LinkedWord":"", "SunMoon":"", "Arabic":"بطاطا", "Symbols":"", "Drawing":"E7", "Letters":"بـ ـطـ ـا طـ ـا", "Transliteration":"baTaTa", "Difficulty":"", "Notes":""},{"Id":"rice", "Kind":"Noun", "Category":"Food", "Form":"", "Article":"", "LinkedWord":"", "SunMoon":"", "Arabic":"رز", "Symbols":"", "Drawing":"E9", "Letters":"ر ز", "Transliteration":"ruz", "Difficulty":"1", "Notes":""},{"Id":"salt", "Kind":"Noun", "Category":"Food", "Form":"", "Article":"", "LinkedWord":"", "SunMoon":"", "Arabic":"مِلْح", "Symbols":"meem_kasrah,lam_sukun", "Drawing":"EB", "Letters":"", "Transliteration":"", "Difficulty":"", "Notes":""},{"Id":"sugar", "Kind":"Noun", "Category":"Food", "Form":"", "Article":"", "LinkedWord":"", "SunMoon":"", "Arabic":"سكر", "Symbols":"", "Drawing":"2191", "Letters":"سـ ـكـ ـر", "Transliteration":"sukkar", "Difficulty":"1", "Notes":""},{"Id":"tea", "Kind":"Noun", "Category":"Food", "Form":"", "Article":"", "LinkedWord":"", "SunMoon":"", "Arabic":"شاي", "Symbols":"", "Drawing":"F4", "Letters":"شـ ـا ي", "Transliteration":"shai", "Difficulty":"1", "Notes":""},{"Id":"the_berry", "Kind":"Noun", "Category":"Food", "Form":"", "Article":"Determinative", "LinkedWord":"berry", "SunMoon":"", "Arabic":"التوت", "Symbols":"", "Drawing":"4C", "Letters":"", "Transliteration":"", "Difficulty":"", "Notes":"sun"},{"Id":"the_bread", "Kind":"Noun", "Category":"Food", "Form":"", "Article":"Determinative", "LinkedWord":"bread", "SunMoon":"", "Arabic":"الخبز", "Symbols":"", "Drawing":"53", "Letters":"", "Transliteration":"", "Difficulty":"", "Notes":"moon"},{"Id":"the_carrot", "Kind":"Noun", "Category":"Food", "Form":"", "Article":"Determinative", "LinkedWord":"carrot", "SunMoon":"", "Arabic":"الجزر", "Symbols":"", "Drawing":"58", "Letters":"", "Transliteration":"", "Difficulty":"", "Notes":"moon"},{"Id":"the_oil", "Kind":"Noun", "Category":"Food", "Form":"", "Article":"Determinative", "LinkedWord":"oil", "SunMoon":"", "Arabic":"الزيت", "Symbols":"", "Drawing":"D9", "Letters":"", "Transliteration":"", "Difficulty":"", "Notes":"sun"},{"Id":"tomato", "Kind":"Noun", "Category":"Food", "Form":"", "Article":"", "LinkedWord":"", "SunMoon":"", "Arabic":"بندورة", "Symbols":"", "Drawing":"FE", "Letters":"بـ ـنـ ـد و ر ة", "Transliteration":"banadora", "Difficulty":"", "Notes":""},{"Id":"vegetables", "Kind":"Noun", "Category":"Food", "Form":"", "Article":"", "LinkedWord":"", "SunMoon":"", "Arabic":"خضر", "Symbols":"", "Drawing":"2E", "Letters":"خـ ـضـ ـر", "Transliteration":"khuDar", "Difficulty":"", "Notes":""},{"Id":"water", "Kind":"Noun", "Category":"Food", "Form":"", "Article":"", "LinkedWord":"", "SunMoon":"", "Arabic":"ماء", "Symbols":"", "Drawing":"2019", "Letters":"م ا ء", "Transliteration":"maa", "Difficulty":"1", "Notes":""},{"Id":"watermelon", "Kind":"Noun", "Category":"Food", "Form":"", "Article":"", "LinkedWord":"", "SunMoon":"", "Arabic":"بطيخ", "Symbols":"", "Drawing":"3F", "Letters":"", "Transliteration":"", "Difficulty":"", "Notes":""},{"Id":"yogurt", "Kind":"Noun", "Category":"Food", "Form":"", "Article":"", "LinkedWord":"", "SunMoon":"", "Arabic":"لبن", "Symbols":"", "Drawing":"2A", "Letters":"لـ ـبـ ـن", "Transliteration":"laban", "Difficulty":"1", "Notes":""},{"Id":"bed", "Kind":"Noun", "Category":"Furniture", "Form":"", "Article":"", "LinkedWord":"", "SunMoon":"", "Arabic":"فراش", "Symbols":"", "Drawing":"4A", "Letters":"فـ ـر ا ش", "Transliteration":"firash", "Difficulty":"", "Notes":""},{"Id":"chair", "Kind":"Noun", "Category":"Furniture", "Form":"", "Article":"", "LinkedWord":"", "SunMoon":"", "Arabic":"كرسي", "Symbols":"", "Drawing":"5A", "Letters":"", "Transliteration":"", "Difficulty":"", "Notes":""},{"Id":"cupboard", "Kind":"Noun", "Category":"Furniture", "Form":"", "Article":"", "LinkedWord":"", "SunMoon":"", "Arabic":"خزانة", "Symbols":"", "Drawing":"C1", "Letters":"", "Transliteration":"", "Difficulty":"", "Notes":""},{"Id":"door", "Kind":"Noun", "Category":"Furniture", "Form":"", "Article":"", "LinkedWord":"", "SunMoon":"", "Arabic":"باب", "Symbols":"", "Drawing":"6C", "Letters":"", "Transliteration":"", "Difficulty":"", "Notes":""},{"Id":"fridge", "Kind":"Noun", "Category":"Furniture", "Form":"", "Article":"", "LinkedWord":"", "SunMoon":"", "Arabic":"ثلاجة", "Symbols":"", "Drawing":"7A", "Letters":"", "Transliteration":"", "Difficulty":"", "Notes":""},{"Id":"furniture", "Kind":"Noun", "Category":"Furniture", "Form":"", "Article":"", "LinkedWord":"", "SunMoon":"", "Arabic":"أثاث", "Symbols":"", "Drawing":"32", "Letters":"", "Transliteration":"", "Difficulty":"", "Notes":""},{"Id":"oven", "Kind":"Noun", "Category":"Furniture", "Form":"", "Article":"", "LinkedWord":"", "SunMoon":"", "Arabic":"فرن", "Symbols":"", "Drawing":"A7", "Letters":"", "Transliteration":"", "Difficulty":"", "Notes":""},{"Id":"table", "Kind":"Noun", "Category":"Furniture", "Form":"", "Article":"", "LinkedWord":"", "SunMoon":"", "Arabic":"طاولة", "Symbols":"", "Drawing":"F3", "Letters":"", "Transliteration":"", "Difficulty":"", "Notes":""},{"Id":"television", "Kind":"Noun", "Category":"Furniture", "Form":"", "Article":"", "LinkedWord":"", "SunMoon":"", "Arabic":"تلفاز", "Symbols":"", "Drawing":"A5", "Letters":"", "Transliteration":"", "Difficulty":"", "Notes":""},{"Id":"the_bed", "Kind":"Noun", "Category":"Furniture", "Form":"", "Article":"Determinative", "LinkedWord":"bed", "SunMoon":"", "Arabic":"الفراش", "Symbols":"", "Drawing":"4A", "Letters":"", "Transliteration":"", "Difficulty":"", "Notes":"moon"},{"Id":"the_table", "Kind":"Noun", "Category":"Furniture", "Form":"", "Article":"Determinative", "LinkedWord":"table", "SunMoon":"", "Arabic":"الطاولة", "Symbols":"", "Drawing":"F3", "Letters":"", "Transliteration":"", "Difficulty":"", "Notes":"sun"},{"Id":"the_window", "Kind":"Noun", "Category":"Furniture", "Form":"", "Article":"Determinative", "LinkedWord":"window", "SunMoon":"", "Arabic":"النافذة", "Symbols":"", "Drawing":"177", "Letters":"", "Transliteration":"", "Difficulty":"", "Notes":"sun"},{"Id":"washing_machine", "Kind":"Noun", "Category":"Furniture", "Form":"", "Article":"", "LinkedWord":"", "SunMoon":"", "Arabic":"غسالة", "Symbols":"", "Drawing":"175", "Letters":"", "Transliteration":"", "Difficulty":"", "Notes":""},{"Id":"window", "Kind":"Noun", "Category":"Furniture", "Form":"", "Article":"", "LinkedWord":"", "SunMoon":"", "Arabic":"نافذة", "Symbols":"", "Drawing":"177", "Letters":"", "Transliteration":"", "Difficulty":"", "Notes":""},{"Id":"beautiful", "Kind":"Adjective", "Category":"General", "Form":"", "Article":"", "LinkedWord":"", "SunMoon":"", "Arabic":"جميل", "Symbols":"", "Drawing":"", "Letters":"جـ ـمـ ـيـ ـل", "Transliteration":"jameel", "Difficulty":"", "Notes":""},{"Id":"clean", "Kind":"Adjective", "Category":"General", "Form":"", "Article":"", "LinkedWord":"", "SunMoon":"", "Arabic":"نظيف", "Symbols":"", "Drawing":"", "Letters":"", "Transliteration":"", "Difficulty":"", "Notes":""},{"Id":"cold", "Kind":"Adjective", "Category":"General", "Form":"", "Article":"", "LinkedWord":"", "SunMoon":"", "Arabic":"برد", "Symbols":"", "Drawing":"", "Letters":"بـ ـر د", "Transliteration":"bard", "Difficulty":"1", "Notes":""},{"Id":"slow", "Kind":"Adjective", "Category":"General", "Form":"", "Article":"", "LinkedWord":"", "SunMoon":"", "Arabic":"بطيء", "Symbols":"", "Drawing":"", "Letters":"", "Transliteration":"", "Difficulty":"", "Notes":""},{"Id":"wonderful", "Kind":"Adjective", "Category":"General", "Form":"", "Article":"", "LinkedWord":"", "SunMoon":"", "Arabic":"رائع", "Symbols":"", "Drawing":"24", "Letters":"", "Transliteration":"", "Difficulty":"", "Notes":""},{"Id":"the_wonderful", "Kind":"Noun", "Category":"General", "Form":"", "Article":"Determinative", "LinkedWord":"wonderful", "SunMoon":"", "Arabic":"الرائع", "Symbols":"", "Drawing":"24", "Letters":"", "Transliteration":"", "Difficulty":"", "Notes":""},{"Id":"carpenter", "Kind":"Noun", "Category":"Job", "Form":"", "Article":"", "LinkedWord":"", "SunMoon":"", "Arabic":"نجّار", "Symbols":"jeem_shaddah", "Drawing":"57", "Letters":"", "Transliteration":"", "Difficulty":"", "Notes":""},{"Id":"doctor", "Kind":"Noun", "Category":"Job", "Form":"", "Article":"", "LinkedWord":"", "SunMoon":"", "Arabic":"طَبيب", "Symbols":"teh_fathah", "Drawing":"6A", "Letters":"", "Transliteration":"", "Difficulty":"", "Notes":""},{"Id":"engineer", "Kind":"Noun", "Category":"Job", "Form":"", "Article":"", "LinkedWord":"", "SunMoon":"", "Arabic":"مهندس", "Symbols":"", "Drawing":"F2", "Letters":"", "Transliteration":"", "Difficulty":"", "Notes":""},{"Id":"farmer", "Kind":"Noun", "Category":"Job", "Form":"", "Article":"", "LinkedWord":"", "SunMoon":"", "Arabic":"فلاح", "Symbols":"", "Drawing":"72", "Letters":"", "Transliteration":"", "Difficulty":"", "Notes":""},{"Id":"player", "Kind":"Noun", "Category":"Job", "Form":"", "Article":"", "LinkedWord":"", "SunMoon":"", "Arabic":"لاعب", "Symbols":"", "Drawing":"20AC", "Letters":"", "Transliteration":"", "Difficulty":"", "Notes":""},{"Id":"policeman", "Kind":"Noun", "Category":"Job", "Form":"", "Article":"", "LinkedWord":"", "SunMoon":"", "Arabic":"شرطي", "Symbols":"", "Drawing":"E6", "Letters":"", "Transliteration":"", "Difficulty":"", "Notes":""},{"Id":"scientist", "Kind":"Noun", "Category":"Job", "Form":"", "Article":"", "LinkedWord":"", "SunMoon":"", "Arabic":"عالم", "Symbols":"", "Drawing":"2C", "Letters":"", "Transliteration":"", "Difficulty":"", "Notes":""},{"Id":"scientist_dual", "Kind":"Noun", "Category":"Job", "Form":"Dual", "Article":"", "LinkedWord":"", "SunMoon":"", "Arabic":"عالمان", "Symbols":"", "Drawing":"2190", "Letters":"", "Transliteration":"", "Difficulty":"", "Notes":""},{"Id":"scientist_plural", "Kind":"Noun", "Category":"Job", "Form":"Plural", "Article":"", "LinkedWord":"", "SunMoon":"", "Arabic":"علماء", "Symbols":"", "Drawing":"2199", "Letters":"", "Transliteration":"", "Difficulty":"", "Notes":""},{"Id":"teacher", "Kind":"Noun", "Category":"Job", "Form":"", "Article":"", "LinkedWord":"", "SunMoon":"", "Arabic":"معلم", "Symbols":"", "Drawing":"F6", "Letters":"", "Transliteration":"", "Difficulty":"", "Notes":""},{"Id":"the_engineer", "Kind":"Noun", "Category":"Job", "Form":"", "Article":"Determinative", "LinkedWord":"engineer", "SunMoon":"", "Arabic":"المهندس", "Symbols":"", "Drawing":"F2", "Letters":"", "Transliteration":"", "Difficulty":"", "Notes":""},{"Id":"the_player", "Kind":"Noun", "Category":"Job", "Form":"", "Article":"Determinative", "LinkedWord":"player", "SunMoon":"", "Arabic":"اللاعب", "Symbols":"", "Drawing":"20AC", "Letters":"", "Transliteration":"", "Difficulty":"", "Notes":"sun"},{"Id":"the_policeman", "Kind":"Noun", "Category":"Job", "Form":"", "Article":"Determinative", "LinkedWord":"policeman", "SunMoon":"", "Arabic":"الشرطي", "Symbols":"", "Drawing":"E6", "Letters":"", "Transliteration":"", "Difficulty":"", "Notes":""},{"Id":"the_scientist", "Kind":"Noun", "Category":"Job", "Form":"", "Article":"Determinative", "LinkedWord":"scientist", "SunMoon":"", "Arabic":"العالم", "Symbols":"", "Drawing":"2C", "Letters":"", "Transliteration":"", "Difficulty":"", "Notes":""},{"Id":"the_worker", "Kind":"Noun", "Category":"Job", "Form":"", "Article":"Determinative", "LinkedWord":"worker", "SunMoon":"", "Arabic":"العامل", "Symbols":"", "Drawing":"27", "Letters":"", "Transliteration":"", "Difficulty":"", "Notes":""},{"Id":"worker", "Kind":"Noun", "Category":"Job", "Form":"", "Article":"", "LinkedWord":"", "SunMoon":"", "Arabic":"عامل", "Symbols":"", "Drawing":"27", "Letters":"", "Transliteration":"", "Difficulty":"", "Notes":""},{"Id":"worker_dual", "Kind":"Noun", "Category":"Job", "Form":"Dual", "Article":"", "LinkedWord":"", "SunMoon":"", "Arabic":"عاملان", "Symbols":"", "Drawing":"201D", "Letters":"", "Transliteration":"", "Difficulty":"", "Notes":""},{"Id":"worker_plural", "Kind":"Noun", "Category":"Job", "Form":"Plural", "Article":"", "LinkedWord":"", "SunMoon":"", "Arabic":"عمال", "Symbols":"", "Drawing":"2018", "Letters":"", "Transliteration":"", "Difficulty":"", "Notes":""},{"Id":"breeze", "Kind":"Noun", "Category":"Nature", "Form":"", "Article":"", "LinkedWord":"", "SunMoon":"", "Arabic":"نسمة", "Symbols":"", "Drawing":"54", "Letters":"", "Transliteration":"", "Difficulty":"", "Notes":""},{"Id":"cloud", "Kind":"Noun", "Category":"Nature", "Form":"", "Article":"", "LinkedWord":"", "SunMoon":"", "Arabic":"غيمة", "Symbols":"", "Drawing":"65", "Letters":"", "Transliteration":"", "Difficulty":"", "Notes":""},{"Id":"flower", "Kind":"Noun", "Category":"Nature", "Form":"", "Article":"", "LinkedWord":"", "SunMoon":"", "Arabic":"ورد", "Symbols":"", "Drawing":"77", "Letters":"و ر د", "Transliteration":"ward", "Difficulty":"1", "Notes":""},{"Id":"forest", "Kind":"Noun", "Category":"Nature", "Form":"", "Article":"", "LinkedWord":"", "SunMoon":"", "Arabic":"غابةٌ", "Symbols":"teh_marbuta_dammah_tanwin", "Drawing":"79", "Letters":"", "Transliteration":"", "Difficulty":"", "Notes":""},{"Id":"islands", "Kind":"Noun", "Category":"Nature", "Form":"", "Article":"", "LinkedWord":"", "SunMoon":"", "Arabic":"جُزُر", "Symbols":"jeem_dammah,zain_dammah", "Drawing":"CE", "Letters":"", "Transliteration":"", "Difficulty":"", "Notes":"Plural"},{"Id":"moon", "Kind":"Noun", "Category":"Nature", "Form":"", "Article":"", "LinkedWord":"", "SunMoon":"", "Arabic":"قمر", "Symbols":"", "Drawing":"D4", "Letters":"", "Transliteration":"", "Difficulty":"", "Notes":""},{"Id":"mountain", "Kind":"Noun", "Category":"Nature", "Form":"", "Article":"", "LinkedWord":"", "SunMoon":"", "Arabic":"جبل", "Symbols":"", "Drawing":"D2", "Letters":"", "Transliteration":"", "Difficulty":"", "Notes":""},{"Id":"mountain_dual", "Kind":"Noun", "Category":"Nature", "Form":"Dual", "Article":"", "LinkedWord":"", "SunMoon":"", "Arabic":"جبلان", "Symbols":"", "Drawing":"B0", "Letters":"", "Transliteration":"", "Difficulty":"", "Notes":""},{"Id":"mountain_plural", "Kind":"Noun", "Category":"Nature", "Form":"Plural", "Article":"", "LinkedWord":"", "SunMoon":"", "Arabic":"جبال", "Symbols":"", "Drawing":"7C", "Letters":"", "Transliteration":"", "Difficulty":"", "Notes":""},{"Id":"rain", "Kind":"Noun", "Category":"Nature", "Form":"", "Article":"", "LinkedWord":"", "SunMoon":"", "Arabic":"مطَر", "Symbols":"teh_fathah", "Drawing":"F0", "Letters":"مـ ـطـ ـر", "Transliteration":"matar", "Difficulty":"1", "Notes":""},{"Id":"river", "Kind":"Noun", "Category":"Nature", "Form":"", "Article":"", "LinkedWord":"", "SunMoon":"", "Arabic":"نهر", "Symbols":"", "Drawing":"EA", "Letters":"", "Transliteration":"", "Difficulty":"", "Notes":""},{"Id":"river_dual", "Kind":"Noun", "Category":"Nature", "Form":"Dual", "Article":"", "LinkedWord":"", "SunMoon":"", "Arabic":"نهران", "Symbols":"", "Drawing":"2195", "Letters":"", "Transliteration":"", "Difficulty":"", "Notes":""},{"Id":"river_plural", "Kind":"Noun", "Category":"Nature", "Form":"Plural", "Article":"", "LinkedWord":"", "SunMoon":"", "Arabic":"أنهار", "Symbols":"", "Drawing":"2194", "Letters":"", "Transliteration":"", "Difficulty":"", "Notes":""},{"Id":"sky", "Kind":"Noun", "Category":"Nature", "Form":"", "Article":"", "LinkedWord":"", "SunMoon":"", "Arabic":"سماء", "Symbols":"hamza", "Drawing":"2026", "Letters":"", "Transliteration":"", "Difficulty":"", "Notes":""},{"Id":"snow", "Kind":"Noun", "Category":"Nature", "Form":"", "Article":"", "LinkedWord":"", "SunMoon":"", "Arabic":"تلج", "Symbols":"", "Drawing":"EF", "Letters":"تـ ـلـ ـج", "Transliteration":"talj", "Difficulty":"1", "Notes":""},{"Id":"summer", "Kind":"Noun", "Category":"Nature", "Form":"", "Article":"", "LinkedWord":"", "SunMoon":"", "Arabic":"صيف", "Symbols":"", "Drawing":"2030", "Letters":"", "Transliteration":"", "Difficulty":"", "Notes":""},{"Id":"sun", "Kind":"Noun", "Category":"Nature", "Form":"", "Article":"", "LinkedWord":"", "SunMoon":"", "Arabic":"شمس", "Symbols":"", "Drawing":"F1", "Letters":"", "Transliteration":"", "Difficulty":"", "Notes":""},{"Id":"the_moon", "Kind":"Noun", "Category":"Nature", "Form":"", "Article":"Determinative", "LinkedWord":"moon", "SunMoon":"", "Arabic":"القمر", "Symbols":"", "Drawing":"D4", "Letters":"", "Transliteration":"", "Difficulty":"", "Notes":"moon"},{"Id":"the_snow", "Kind":"Noun", "Category":"Nature", "Form":"", "Article":"Determinative", "LinkedWord":"snow", "SunMoon":"", "Arabic":"الثلج", "Symbols":"", "Drawing":"EF", "Letters":"", "Transliteration":"", "Difficulty":"", "Notes":"sun"},{"Id":"the_sun", "Kind":"Noun", "Category":"Nature", "Form":"", "Article":"Determinative", "LinkedWord":"sun", "SunMoon":"", "Arabic":"الشمس", "Symbols":"", "Drawing":"F1", "Letters":"", "Transliteration":"", "Difficulty":"", "Notes":"sun"},{"Id":"tree", "Kind":"Noun", "Category":"Nature", "Form":"", "Article":"", "LinkedWord":"", "SunMoon":"", "Arabic":"شجر", "Symbols":"", "Drawing":"FB", "Letters":"شـ ـجـ ـر", "Transliteration":"shajar", "Difficulty":"1", "Notes":""},{"Id":"rainy", "Kind":"Adjective", "Category":"Nature ", "Form":"", "Article":"", "LinkedWord":"", "SunMoon":"", "Arabic":"ماطر", "Symbols":"", "Drawing":"", "Letters":"", "Transliteration":"", "Difficulty":"", "Notes":""},{"Id":"number_00", "Kind":"Noun", "Category":"Number", "Form":"", "Article":"", "LinkedWord":"", "SunMoon":"", "Arabic":"صفر", "Symbols":"", "Drawing":"2669", "Letters":"", "Transliteration":"", "Difficulty":"", "Notes":""},{"Id":"number_01", "Kind":"Noun", "Category":"Number", "Form":"", "Article":"", "LinkedWord":"", "SunMoon":"", "Arabic":"واحد", "Symbols":"", "Drawing":"266A", "Letters":"", "Transliteration":"", "Difficulty":"", "Notes":""},{"Id":"number_02", "Kind":"Noun", "Category":"Number", "Form":"", "Article":"", "LinkedWord":"", "SunMoon":"", "Arabic":"اثنان", "Symbols":"", "Drawing":"266B", "Letters":"", "Transliteration":"", "Difficulty":"", "Notes":""},{"Id":"number_03", "Kind":"Noun", "Category":"Number", "Form":"", "Article":"", "LinkedWord":"", "SunMoon":"", "Arabic":"ثلاثة", "Symbols":"", "Drawing":"266C", "Letters":"", "Transliteration":"", "Difficulty":"", "Notes":""},{"Id":"number_04", "Kind":"Noun", "Category":"Number", "Form":"", "Article":"", "LinkedWord":"", "SunMoon":"", "Arabic":"أربعة", "Symbols":"", "Drawing":"266D", "Letters":"", "Transliteration":"", "Difficulty":"", "Notes":""},{"Id":"number_05", "Kind":"Noun", "Category":"Number", "Form":"", "Article":"", "LinkedWord":"", "SunMoon":"", "Arabic":"خمسة", "Symbols":"", "Drawing":"266E", "Letters":"", "Transliteration":"", "Difficulty":"", "Notes":""},{"Id":"number_06", "Kind":"Noun", "Category":"Number", "Form":"", "Article":"", "LinkedWord":"", "SunMoon":"", "Arabic":"ستة", "Symbols":"", "Drawing":"266F", "Letters":"", "Transliteration":"", "Difficulty":"", "Notes":""},{"Id":"number_07", "Kind":"Noun", "Category":"Number", "Form":"", "Article":"", "LinkedWord":"", "SunMoon":"", "Arabic":"سبعةٌ", "Symbols":"teh_marbuta_dammah_tanwin", "Drawing":"1D184", "Letters":"", "Transliteration":"", "Difficulty":"", "Notes":""},{"Id":"number_08", "Kind":"Noun", "Category":"Number", "Form":"", "Article":"", "LinkedWord":"", "SunMoon":"", "Arabic":"ثمانية", "Symbols":"", "Drawing":"1D183", "Letters":"", "Transliteration":"", "Difficulty":"", "Notes":""},{"Id":"number_09", "Kind":"Noun", "Category":"Number", "Form":"", "Article":"", "LinkedWord":"", "SunMoon":"", "Arabic":"تسعة", "Symbols":"", "Drawing":"1D114", "Letters":"", "Transliteration":"", "Difficulty":"", "Notes":""},{"Id":"number_10", "Kind":"Noun", "Category":"Number", "Form":"", "Article":"", "LinkedWord":"", "SunMoon":"", "Arabic":"عشرة", "Symbols":"", "Drawing":"1D115", "Letters":"", "Transliteration":"", "Difficulty":"", "Notes":""},{"Id":"number_11", "Kind":"Noun", "Category":"Number", "Form":"", "Article":"", "LinkedWord":"", "SunMoon":"", "Arabic":"احد عشر", "Symbols":"", "Drawing":"1D112", "Letters":"", "Transliteration":"", "Difficulty":"", "Notes":""},{"Id":"number_12", "Kind":"Noun", "Category":"Number", "Form":"", "Article":"", "LinkedWord":"", "SunMoon":"", "Arabic":"اثني عشر", "Symbols":"", "Drawing":"1D15C", "Letters":"", "Transliteration":"", "Difficulty":"", "Notes":""},{"Id":"number_13", "Kind":"Noun", "Category":"Number", "Form":"", "Article":"", "LinkedWord":"", "SunMoon":"", "Arabic":"ثلاثة عشر", "Symbols":"", "Drawing":"1D1B8", "Letters":"", "Transliteration":"", "Difficulty":"", "Notes":""},{"Id":"number_14", "Kind":"Noun", "Category":"Number", "Form":"", "Article":"", "LinkedWord":"", "SunMoon":"", "Arabic":"أربعة عشر", "Symbols":"", "Drawing":"1D1C3", "Letters":"", "Transliteration":"", "Difficulty":"", "Notes":""},{"Id":"number_15", "Kind":"Noun", "Category":"Number", "Form":"", "Article":"", "LinkedWord":"", "SunMoon":"", "Arabic":"خمسة عشر", "Symbols":"", "Drawing":"1D121", "Letters":"", "Transliteration":"", "Difficulty":"", "Notes":""},{"Id":"number_16", "Kind":"Noun", "Category":"Number", "Form":"", "Article":"", "LinkedWord":"", "SunMoon":"", "Arabic":"ستة عشر", "Symbols":"", "Drawing":"1D113", "Letters":"", "Transliteration":"", "Difficulty":"", "Notes":""},{"Id":"number_17", "Kind":"Noun", "Category":"Number", "Form":"", "Article":"", "LinkedWord":"", "SunMoon":"", "Arabic":"سبعة عشر", "Symbols":"", "Drawing":"1D104", "Letters":"", "Transliteration":"", "Difficulty":"", "Notes":""},{"Id":"number_18", "Kind":"Noun", "Category":"Number", "Form":"", "Article":"", "LinkedWord":"", "SunMoon":"", "Arabic":"ثمانية عشر", "Symbols":"", "Drawing":"1D145", "Letters":"", "Transliteration":"", "Difficulty":"", "Notes":""},{"Id":"number_19", "Kind":"Noun", "Category":"Number", "Form":"", "Article":"", "LinkedWord":"", "SunMoon":"", "Arabic":"تسعة عشر", "Symbols":"", "Drawing":"1D1D7", "Letters":"", "Transliteration":"", "Difficulty":"", "Notes":""},{"Id":"number_20", "Kind":"Noun", "Category":"Number", "Form":"", "Article":"", "LinkedWord":"", "SunMoon":"", "Arabic":"عشرون", "Symbols":"", "Drawing":"1D1D5", "Letters":"", "Transliteration":"", "Difficulty":"", "Notes":""},{"Id":"number_2000", "Kind":"Noun", "Category":"Number", "Form":"", "Article":"", "LinkedWord":"", "SunMoon":"", "Arabic":"الفين", "Symbols":"", "Drawing":"1D15B", "Letters":"", "Transliteration":"", "Difficulty":"", "Notes":""},{"Id":"number_o01", "Kind":"Noun", "Category":"NumberOrdinal", "Form":"", "Article":"", "LinkedWord":"", "SunMoon":"", "Arabic":"الأول", "Symbols":"", "Drawing":"1D15A", "Letters":"", "Transliteration":"", "Difficulty":"", "Notes":""},{"Id":"number_o02", "Kind":"Noun", "Category":"NumberOrdinal", "Form":"", "Article":"", "LinkedWord":"", "SunMoon":"", "Arabic":"الثاني", "Symbols":"", "Drawing":"1D10C", "Letters":"", "Transliteration":"", "Difficulty":"", "Notes":""},{"Id":"number_o03", "Kind":"Noun", "Category":"NumberOrdinal", "Form":"", "Article":"", "LinkedWord":"", "SunMoon":"", "Arabic":"الثالث", "Symbols":"", "Drawing":"1D134", "Letters":"", "Transliteration":"", "Difficulty":"", "Notes":""},{"Id":"number_o04", "Kind":"Noun", "Category":"NumberOrdinal", "Form":"", "Article":"", "LinkedWord":"", "SunMoon":"", "Arabic":"الرابع", "Symbols":"", "Drawing":"1D192", "Letters":"", "Transliteration":"", "Difficulty":"", "Notes":""},{"Id":"number_o05", "Kind":"Noun", "Category":"NumberOrdinal", "Form":"", "Article":"", "LinkedWord":"", "SunMoon":"", "Arabic":"الخامس", "Symbols":"", "Drawing":"1D1CF", "Letters":"", "Transliteration":"", "Difficulty":"", "Notes":""},{"Id":"number_o06", "Kind":"Noun", "Category":"NumberOrdinal", "Form":"", "Article":"", "LinkedWord":"", "SunMoon":"", "Arabic":"السادس", "Symbols":"", "Drawing":"1D135", "Letters":"", "Transliteration":"", "Difficulty":"", "Notes":""},{"Id":"number_o07", "Kind":"Noun", "Category":"NumberOrdinal", "Form":"", "Article":"", "LinkedWord":"", "SunMoon":"", "Arabic":"السابع", "Symbols":"", "Drawing":"1D10A", "Letters":"", "Transliteration":"", "Difficulty":"", "Notes":""},{"Id":"number_o08", "Kind":"Noun", "Category":"NumberOrdinal", "Form":"", "Article":"", "LinkedWord":"", "SunMoon":"", "Arabic":"الثامن", "Symbols":"", "Drawing":"1D109", "Letters":"", "Transliteration":"", "Difficulty":"", "Notes":""},{"Id":"number_o09", "Kind":"Noun", "Category":"NumberOrdinal", "Form":"", "Article":"", "LinkedWord":"", "SunMoon":"", "Arabic":"التاسع", "Symbols":"", "Drawing":"1D1B4", "Letters":"", "Transliteration":"", "Difficulty":"", "Notes":""},{"Id":"number_o10", "Kind":"Noun", "Category":"NumberOrdinal", "Form":"", "Article":"", "LinkedWord":"", "SunMoon":"", "Arabic":"العاشر", "Symbols":"", "Drawing":"1D1B5", "Letters":"", "Transliteration":"", "Difficulty":"", "Notes":""},{"Id":"number_o11", "Kind":"Noun", "Category":"NumberOrdinal", "Form":"", "Article":"", "LinkedWord":"", "SunMoon":"", "Arabic":"الحادي عشر", "Symbols":"", "Drawing":"", "Letters":"", "Transliteration":"", "Difficulty":"", "Notes":""},{"Id":"active", "Kind":"Adjective", "Category":"People", "Form":"", "Article":"", "LinkedWord":"", "SunMoon":"", "Arabic":"نشيط", "Symbols":"", "Drawing":"", "Letters":"نـ ـشـ ـيـ ـط", "Transliteration":"nasheet ", "Difficulty":"", "Notes":""},{"Id":"brave", "Kind":"Adjective", "Category":"People", "Form":"", "Article":"", "LinkedWord":"", "SunMoon":"", "Arabic":"شجاع", "Symbols":"", "Drawing":"", "Letters":"", "Transliteration":"", "Difficulty":"", "Notes":""},{"Id":"happy", "Kind":"Adjective", "Category":"People", "Form":"", "Article":"", "LinkedWord":"", "SunMoon":"", "Arabic":"سعيد", "Symbols":"", "Drawing":"", "Letters":"", "Transliteration":"", "Difficulty":"", "Notes":""},{"Id":"insistent", "Kind":"Adjective", "Category":"People", "Form":"", "Article":"", "LinkedWord":"", "SunMoon":"", "Arabic":"مُلِحّ", "Symbols":"meem_dammah,lam_kasrah,hah_shaddah", "Drawing":"", "Letters":"", "Transliteration":"", "Difficulty":"", "Notes":""},{"Id":"lazy", "Kind":"Adjective", "Category":"People", "Form":"", "Article":"", "LinkedWord":"", "SunMoon":"", "Arabic":"كسول", "Symbols":"", "Drawing":"", "Letters":"", "Transliteration":"", "Difficulty":"", "Notes":""},{"Id":"the_active", "Kind":"Adjective", "Category":"People", "Form":"", "Article":"Determinative", "LinkedWord":"active", "SunMoon":"", "Arabic":"النشيط", "Symbols":"", "Drawing":"", "Letters":"", "Transliteration":"", "Difficulty":"", "Notes":""},{"Id":"the_happy", "Kind":"Adjective", "Category":"People", "Form":"", "Article":"Determinative", "LinkedWord":"happy", "SunMoon":"", "Arabic":"السعيد", "Symbols":"", "Drawing":"", "Letters":"", "Transliteration":"", "Difficulty":"", "Notes":""},{"Id":"the_lazy", "Kind":"Adjective", "Category":"People", "Form":"", "Article":"Determinative", "LinkedWord":"lazy", "SunMoon":"", "Arabic":"الكسول", "Symbols":"", "Drawing":"", "Letters":"", "Transliteration":"", "Difficulty":"", "Notes":""},{"Id":"the_sad", "Kind":"Adjective", "Category":"People", "Form":"", "Article":"Determinative", "LinkedWord":"sad", "SunMoon":"", "Arabic":"الحزين", "Symbols":"", "Drawing":"", "Letters":"", "Transliteration":"", "Difficulty":"", "Notes":""},{"Id":"virtuous", "Kind":"Adjective", "Category":"People", "Form":"", "Article":"", "LinkedWord":"", "SunMoon":"", "Arabic":"نزيه", "Symbols":"", "Drawing":"", "Letters":"", "Transliteration":"", "Difficulty":"", "Notes":""},{"Id":"safe", "Kind":"Adjective", "Category":"Place", "Form":"", "Article":"", "LinkedWord":"", "SunMoon":"", "Arabic":"آمِنْ", "Symbols":"alef_maddah,meem_kasrah,noon_sukun", "Drawing":"", "Letters":"", "Transliteration":"", "Difficulty":"", "Notes":""},{"Id":"bank", "Kind":"Noun", "Category":"Place", "Form":"", "Article":"", "LinkedWord":"", "SunMoon":"", "Arabic":"مصرف", "Symbols":"", "Drawing":"47", "Letters":"بـ ـنـ ـك", "Transliteration":"bank", "Difficulty":"", "Notes":""},{"Id":"classroom", "Kind":"Noun", "Category":"Place", "Form":"", "Article":"", "LinkedWord":"", "SunMoon":"", "Arabic":"صف", "Symbols":"", "Drawing":"30", "Letters":"", "Transliteration":"", "Difficulty":"", "Notes":""},{"Id":"club", "Kind":"Noun", "Category":"Place", "Form":"", "Article":"", "LinkedWord":"", "SunMoon":"", "Arabic":"منتدى", "Symbols":"", "Drawing":"", "Letters":"", "Transliteration":"", "Difficulty":"", "Notes":""},{"Id":"field", "Kind":"Noun", "Category":"Place", "Form":"", "Article":"", "LinkedWord":"", "SunMoon":"", "Arabic":"حقل", "Symbols":"", "Drawing":"73", "Letters":"", "Transliteration":"", "Difficulty":"", "Notes":""},{"Id":"garden", "Kind":"Noun", "Category":"Place", "Form":"", "Article":"", "LinkedWord":"", "SunMoon":"", "Arabic":"بُستان", "Symbols":"beh_dammah", "Drawing":"C2", "Letters":"", "Transliteration":"", "Difficulty":"", "Notes":""},{"Id":"ground", "Kind":"Noun", "Category":"Place", "Form":"", "Article":"", "LinkedWord":"", "SunMoon":"", "Arabic":"أرض", "Symbols":"", "Drawing":"37", "Letters":"", "Transliteration":"", "Difficulty":"", "Notes":""},{"Id":"hospital", "Kind":"Noun", "Category":"Place", "Form":"", "Article":"", "LinkedWord":"", "SunMoon":"", "Arabic":"مستشفى", "Symbols":"", "Drawing":"CB", "Letters":"", "Transliteration":"", "Difficulty":"", "Notes":""},{"Id":"house", "Kind":"Noun", "Category":"Place", "Form":"", "Article":"", "LinkedWord":"", "SunMoon":"", "Arabic":"بيت", "Symbols":"", "Drawing":"C8", "Letters":"", "Transliteration":"", "Difficulty":"", "Notes":""},{"Id":"market", "Kind":"Noun", "Category":"Place", "Form":"", "Article":"", "LinkedWord":"", "SunMoon":"", "Arabic":"سوق", "Symbols":"", "Drawing":"AB", "Letters":"", "Transliteration":"", "Difficulty":"", "Notes":""},{"Id":"OokaDH", "Kind":"Noun", "Category":"Place", "Form":"", "Article":"", "LinkedWord":"", "SunMoon":"", "Arabic":"عكاظ", "Symbols":"", "Drawing":"A9", "Letters":"", "Transliteration":"", "Difficulty":"", "Notes":"name of a place in Saudi"},{"Id":"playground", "Kind":"Noun", "Category":"Place", "Form":"", "Article":"", "LinkedWord":"", "SunMoon":"", "Arabic":"ملعب", "Symbols":"", "Drawing":"", "Letters":"", "Transliteration":"", "Difficulty":"", "Notes":""},{"Id":"restaurant", "Kind":"Noun", "Category":"Place", "Form":"", "Article":"", "LinkedWord":"", "SunMoon":"", "Arabic":"مطعَم", "Symbols":"ain_fathah", "Drawing":"26", "Letters":"", "Transliteration":"", "Difficulty":"", "Notes":""},{"Id":"room", "Kind":"Noun", "Category":"Place", "Form":"", "Article":"", "LinkedWord":"", "SunMoon":"", "Arabic":"غرفة", "Symbols":"", "Drawing":"3A", "Letters":"", "Transliteration":"", "Difficulty":"", "Notes":""},{"Id":"school", "Kind":"Noun", "Category":"Place", "Form":"", "Article":"", "LinkedWord":"", "SunMoon":"", "Arabic":"مدرسة", "Symbols":"", "Drawing":"2196", "Letters":"", "Transliteration":"", "Difficulty":"", "Notes":""},{"Id":"shop", "Kind":"Noun", "Category":"Place", "Form":"", "Article":"", "LinkedWord":"", "SunMoon":"", "Arabic":"دكانٍ", "Symbols":"noon_kasrah_tanwin", "Drawing":"2198", "Letters":"", "Transliteration":"", "Difficulty":"", "Notes":""},{"Id":"station", "Kind":"Noun", "Category":"Place", "Form":"", "Article":"", "LinkedWord":"", "SunMoon":"", "Arabic":"محطة", "Symbols":"", "Drawing":"2197", "Letters":"", "Transliteration":"", "Difficulty":"", "Notes":""},{"Id":"the_playground", "Kind":"Noun", "Category":"Place", "Form":"", "Article":"Determinative", "LinkedWord":"playground", "SunMoon":"", "Arabic":"الملعب", "Symbols":"", "Drawing":"21", "Letters":"", "Transliteration":"", "Difficulty":"", "Notes":""},{"Id":"the_room", "Kind":"Noun", "Category":"Place", "Form":"", "Article":"Determinative", "LinkedWord":"room", "SunMoon":"", "Arabic":"الغرفة", "Symbols":"", "Drawing":"3A", "Letters":"", "Transliteration":"", "Difficulty":"", "Notes":"moon"},{"Id":"toilet", "Kind":"Noun", "Category":"Place", "Form":"", "Article":"", "LinkedWord":"", "SunMoon":"", "Arabic":"مرحاض", "Symbols":"", "Drawing":"153", "Letters":"", "Transliteration":"", "Difficulty":"", "Notes":""},{"Id":"tower", "Kind":"Noun", "Category":"Place", "Form":"", "Article":"", "LinkedWord":"", "SunMoon":"", "Arabic":"برج", "Symbols":"", "Drawing":"FA", "Letters":"", "Transliteration":"", "Difficulty":"", "Notes":""},{"Id":"in", "Kind":"Preposition", "Category":"Position", "Form":"", "Article":"", "LinkedWord":"", "SunMoon":"", "Arabic":"في", "Symbols":"", "Drawing":"", "Letters":"", "Transliteration":"", "Difficulty":"", "Notes":""},{"Id":"on", "Kind":"Preposition", "Category":"Position", "Form":"", "Article":"", "LinkedWord":"", "SunMoon":"", "Arabic":"على", "Symbols":"alef_maqsura", "Drawing":"", "Letters":"", "Transliteration":"", "Difficulty":"", "Notes":""},{"Id":"triangle", "Kind":"Noun", "Category":"Shape", "Form":"", "Article":"", "LinkedWord":"", "SunMoon":"", "Arabic":"مثلث", "Symbols":"", "Drawing":"FC", "Letters":"", "Transliteration":"", "Difficulty":"", "Notes":""},{"Id":"big", "Kind":"Adjective", "Category":"Size", "Form":"", "Article":"", "LinkedWord":"", "SunMoon":"", "Arabic":"كبير", "Symbols":"", "Drawing":"", "Letters":"كـ ـبـ ـيـ ـر", "Transliteration":"kabeer", "Difficulty":"", "Notes":""},{"Id":"small", "Kind":"Adjective", "Category":"Size", "Form":"", "Article":"", "LinkedWord":"", "SunMoon":"", "Arabic":"صغير", "Symbols":"", "Drawing":"", "Letters":"", "Transliteration":"", "Difficulty":"", "Notes":""},{"Id":"basketball", "Kind":"Noun", "Category":"Sport", "Form":"", "Article":"", "LinkedWord":"", "SunMoon":"", "Arabic":"كرة السلة", "Symbols":"", "Drawing":"48", "Letters":"كـ ـر ة  ا لـ ـسـ ـلـ ـة", "Transliteration":"kurat assalla", "Difficulty":"", "Notes":""},{"Id":"football", "Kind":"Noun", "Category":"Sport", "Form":"", "Article":"", "LinkedWord":"", "SunMoon":"", "Arabic":"كرة القدم", "Symbols":"", "Drawing":"78", "Letters":"", "Transliteration":"", "Difficulty":"", "Notes":""},{"Id":"ball", "Kind":"Noun", "Category":"Thing", "Form":"", "Article":"", "LinkedWord":"", "SunMoon":"", "Arabic":"كرة", "Symbols":"", "Drawing":"A3", "Letters":"", "Transliteration":"", "Difficulty":"", "Notes":""},{"Id":"book", "Kind":"Noun", "Category":"Thing", "Form":"", "Article":"", "LinkedWord":"", "SunMoon":"", "Arabic":"كتاب", "Symbols":"", "Drawing":"4E", "Letters":"كـ ـتـ ـا ب", "Transliteration":"kitaab", "Difficulty":"", "Notes":""},{"Id":"books", "Kind":"Noun", "Category":"Thing", "Form":"", "Article":"", "LinkedWord":"", "SunMoon":"", "Arabic":"كُتُب", "Symbols":"kaf_dammah,teh_dammah", "Drawing":"4F", "Letters":"كُـ ـتـُ ـب", "Transliteration":"kutub", "Difficulty":"", "Notes":""},{"Id":"box", "Kind":"Noun", "Category":"Thing", "Form":"", "Article":"", "LinkedWord":"", "SunMoon":"", "Arabic":"صندوق", "Symbols":"", "Drawing":"50", "Letters":"", "Transliteration":"sunduuq", "Difficulty":"", "Notes":""},{"Id":"flag", "Kind":"Noun", "Category":"Thing", "Form":"", "Article":"", "LinkedWord":"", "SunMoon":"", "Arabic":"علَم", "Symbols":"lam_fathah", "Drawing":"76", "Letters":"", "Transliteration":"", "Difficulty":"", "Notes":""},{"Id":"glue", "Kind":"Noun", "Category":"Thing", "Form":"", "Article":"", "LinkedWord":"", "SunMoon":"", "Arabic":"صَمغ", "Symbols":"sad_fathah", "Drawing":"C5", "Letters":"", "Transliteration":"", "Difficulty":"", "Notes":""},{"Id":"needle", "Kind":"Noun", "Category":"Thing", "Form":"", "Article":"", "LinkedWord":"", "SunMoon":"", "Arabic":"إبرة", "Symbols":"alef_hamza_low", "Drawing":"DE", "Letters":"", "Transliteration":"", "Difficulty":"", "Notes":""},{"Id":"notebook", "Kind":"Noun", "Category":"Thing", "Form":"", "Article":"", "LinkedWord":"", "SunMoon":"", "Arabic":"دفتَر", "Symbols":"teh_fathah", "Drawing":"DC", "Letters":"د فـ ـتـ ـر", "Transliteration":"daftar", "Difficulty":"", "Notes":""},{"Id":"paper", "Kind":"Noun", "Category":"Thing", "Form":"", "Article":"", "LinkedWord":"", "SunMoon":"", "Arabic":"ورق", "Symbols":"", "Drawing":"E1", "Letters":"و ر ق", "Transliteration":"waraq", "Difficulty":"", "Notes":""},{"Id":"pencil", "Kind":"Noun", "Category":"Thing", "Form":"", "Article":"", "LinkedWord":"", "SunMoon":"", "Arabic":"قلم", "Symbols":"", "Drawing":"E5", "Letters":"قـ ـلـ ـم", "Transliteration":"qalam", "Difficulty":"", "Notes":""},{"Id":"scissors", "Kind":"Noun", "Category":"Thing", "Form":"", "Article":"", "LinkedWord":"", "SunMoon":"", "Arabic":"مقص", "Symbols":"", "Drawing":"E8", "Letters":"", "Transliteration":"", "Difficulty":"", "Notes":""},{"Id":"the_ball", "Kind":"Noun", "Category":"Thing", "Form":"", "Article":"Determinative", "LinkedWord":"ball", "SunMoon":"", "Arabic":"الكرة", "Symbols":"", "Drawing":"A3", "Letters":"", "Transliteration":"", "Difficulty":"", "Notes":""},{"Id":"the_book", "Kind":"Noun", "Category":"Thing", "Form":"", "Article":"Determinative", "LinkedWord":"book", "SunMoon":"", "Arabic":"الكتاب", "Symbols":"", "Drawing":"4E", "Letters":"", "Transliteration":"", "Difficulty":"", "Notes":"moon"},{"Id":"the_box", "Kind":"Noun", "Category":"Thing", "Form":"", "Article":"Determinative", "LinkedWord":"box", "SunMoon":"", "Arabic":"الصندوق", "Symbols":"", "Drawing":"50", "Letters":"", "Transliteration":"", "Difficulty":"", "Notes":"sun"},{"Id":"last", "Kind":"Adjective", "Category":"Time", "Form":"", "Article":"", "LinkedWord":"", "SunMoon":"", "Arabic":"الماضي", "Symbols":"", "Drawing":"", "Letters":"", "Transliteration":"", "Difficulty":"", "Notes":""},{"Id":"next", "Kind":"Adjective", "Category":"Time", "Form":"", "Article":"", "LinkedWord":"", "SunMoon":"", "Arabic":"القادم", "Symbols":"", "Drawing":"", "Letters":"", "Transliteration":"", "Difficulty":"", "Notes":""},{"Id":"now", "Kind":"Adverb", "Category":"Time", "Form":"", "Article":"", "LinkedWord":"", "SunMoon":"", "Arabic":"الآن", "Symbols":"alef_maddah", "Drawing":"", "Letters":"", "Transliteration":"", "Difficulty":"", "Notes":""},{"Id":"today", "Kind":"Adverb", "Category":"Time", "Form":"", "Article":"", "LinkedWord":"", "SunMoon":"", "Arabic":"اليوم", "Symbols":"", "Drawing":"", "Letters":"", "Transliteration":"", "Difficulty":"", "Notes":""},{"Id":"tomorrow", "Kind":"Adverb", "Category":"Time", "Form":"", "Article":"", "LinkedWord":"", "SunMoon":"", "Arabic":"غداً", "Symbols":"alef_fathah_tanwin", "Drawing":"", "Letters":"", "Transliteration":"", "Difficulty":"", "Notes":""},{"Id":"yesterday", "Kind":"Adverb", "Category":"Time", "Form":"", "Article":"", "LinkedWord":"", "SunMoon":"", "Arabic":"البارحة", "Symbols":"", "Drawing":"", "Letters":"", "Transliteration":"", "Difficulty":"", "Notes":""},{"Id":"day", "Kind":"Noun", "Category":"Time", "Form":"", "Article":"", "LinkedWord":"", "SunMoon":"", "Arabic":"يوم", "Symbols":"", "Drawing":"2B", "Letters":"يـ ـو م", "Transliteration":"yawm", "Difficulty":"", "Notes":""},{"Id":"day_friday", "Kind":"Noun", "Category":"Time", "Form":"", "Article":"", "LinkedWord":"", "SunMoon":"", "Arabic":"الجمعة", "Symbols":"", "Drawing":"2212", "Letters":"", "Transliteration":"", "Difficulty":"", "Notes":""},{"Id":"day_monday", "Kind":"Noun", "Category":"Time", "Form":"", "Article":"", "LinkedWord":"", "SunMoon":"", "Arabic":"الاثنين", "Symbols":"", "Drawing":"D7", "Letters":"", "Transliteration":"", "Difficulty":"", "Notes":""},{"Id":"day_saturday", "Kind":"Noun", "Category":"Time", "Form":"", "Article":"", "LinkedWord":"", "SunMoon":"", "Arabic":"السبت", "Symbols":"", "Drawing":"F7", "Letters":"", "Transliteration":"", "Difficulty":"", "Notes":""},{"Id":"day_sunday", "Kind":"Noun", "Category":"Time", "Form":"", "Article":"", "LinkedWord":"", "SunMoon":"", "Arabic":"الأحد", "Symbols":"", "Drawing":"3D", "Letters":"", "Transliteration":"", "Difficulty":"", "Notes":""},{"Id":"day_thursday", "Kind":"Noun", "Category":"Time", "Form":"", "Article":"", "LinkedWord":"", "SunMoon":"", "Arabic":"الخميس", "Symbols":"", "Drawing":"2260", "Letters":"", "Transliteration":"", "Difficulty":"", "Notes":""},{"Id":"day_tuesday", "Kind":"Noun", "Category":"Time", "Form":"", "Article":"", "LinkedWord":"", "SunMoon":"", "Arabic":"الثلاثاء", "Symbols":"hamza", "Drawing":"3E", "Letters":"", "Transliteration":"", "Difficulty":"", "Notes":""},{"Id":"day_wednesday", "Kind":"Noun", "Category":"Time", "Form":"", "Article":"", "LinkedWord":"", "SunMoon":"", "Arabic":"الأربعاء", "Symbols":"hamza", "Drawing":"3C", "Letters":"", "Transliteration":"", "Difficulty":"", "Notes":""},{"Id":"evening", "Kind":"Noun", "Category":"Time", "Form":"", "Article":"", "LinkedWord":"", "SunMoon":"", "Arabic":"مساء", "Symbols":"", "Drawing":"7D", "Letters":"", "Transliteration":"", "Difficulty":"", "Notes":"added by stefano"},{"Id":"fall", "Kind":"Noun", "Category":"Time", "Form":"", "Article":"", "LinkedWord":"", "SunMoon":"", "Arabic":"خريف", "Symbols":"", "Drawing":"7B", "Letters":"", "Transliteration":"", "Difficulty":"", "Notes":""},{"Id":"hour", "Kind":"Noun", "Category":"Time", "Form":"", "Article":"", "LinkedWord":"", "SunMoon":"", "Arabic":"ساعة", "Symbols":"", "Drawing":"38", "Letters":"سـ ـا عـ ـة", "Transliteration":"sa’a", "Difficulty":"", "Notes":""},{"Id":"month", "Kind":"Noun", "Category":"Time", "Form":"", "Article":"", "LinkedWord":"", "SunMoon":"", "Arabic":"شهر", "Symbols":"", "Drawing":"2265", "Letters":"شـ ـهـ ـر", "Transliteration":"shahr", "Difficulty":"", "Notes":""},{"Id":"month_april", "Kind":"Noun", "Category":"Time", "Form":"", "Article":"", "LinkedWord":"", "SunMoon":"", "Arabic":"نيسان", "Symbols":"", "Drawing":"2264", "Letters":"", "Transliteration":"", "Difficulty":"", "Notes":""},{"Id":"month_august", "Kind":"Noun", "Category":"Time", "Form":"", "Article":"", "LinkedWord":"", "SunMoon":"", "Arabic":"آب", "Symbols":"alef_maddah", "Drawing":"B1", "Letters":"", "Transliteration":"", "Difficulty":"", "Notes":""},{"Id":"month_december", "Kind":"Noun", "Category":"Time", "Form":"", "Article":"", "LinkedWord":"", "SunMoon":"", "Arabic":"كانون الأول", "Symbols":"", "Drawing":"2248", "Letters":"", "Transliteration":"", "Difficulty":"", "Notes":""},{"Id":"month_february", "Kind":"Noun", "Category":"Time", "Form":"", "Article":"", "LinkedWord":"", "SunMoon":"", "Arabic":"شباط", "Symbols":"", "Drawing":"7E", "Letters":"", "Transliteration":"", "Difficulty":"", "Notes":""},{"Id":"month_january", "Kind":"Noun", "Category":"Time", "Form":"", "Article":"", "LinkedWord":"", "SunMoon":"", "Arabic":"كانون الثاني", "Symbols":"", "Drawing":"AC", "Letters":"", "Transliteration":"", "Difficulty":"", "Notes":""},{"Id":"month_july", "Kind":"Noun", "Category":"Time", "Form":"", "Article":"", "LinkedWord":"", "SunMoon":"", "Arabic":"تموز", "Symbols":"", "Drawing":"2205", "Letters":"", "Transliteration":"", "Difficulty":"", "Notes":""},{"Id":"month_june", "Kind":"Noun", "Category":"Time", "Form":"", "Article":"", "LinkedWord":"", "SunMoon":"", "Arabic":"حزيران", "Symbols":"", "Drawing":"221E", "Letters":"", "Transliteration":"", "Difficulty":"", "Notes":""},{"Id":"month_march", "Kind":"Noun", "Category":"Time", "Form":"", "Article":"", "LinkedWord":"", "SunMoon":"", "Arabic":"آذار", "Symbols":"", "Drawing":"222B", "Letters":"", "Transliteration":"", "Difficulty":"", "Notes":""},{"Id":"month_may", "Kind":"Noun", "Category":"Time", "Form":"", "Article":"", "LinkedWord":"", "SunMoon":"", "Arabic":"أيار", "Symbols":"", "Drawing":"220F", "Letters":"", "Transliteration":"", "Difficulty":"", "Notes":""},{"Id":"month_november", "Kind":"Noun", "Category":"Time", "Form":"", "Article":"", "LinkedWord":"", "SunMoon":"", "Arabic":"تشرين الثاني", "Symbols":"", "Drawing":"2211", "Letters":"", "Transliteration":"", "Difficulty":"", "Notes":""},{"Id":"month_october", "Kind":"Noun", "Category":"Time", "Form":"", "Article":"", "LinkedWord":"", "SunMoon":"", "Arabic":"تشرين الأول", "Symbols":"", "Drawing":"221A", "Letters":"", "Transliteration":"", "Difficulty":"", "Notes":""},{"Id":"month_september", "Kind":"Noun", "Category":"Time", "Form":"", "Article":"", "LinkedWord":"", "SunMoon":"", "Arabic":"أيلول", "Symbols":"", "Drawing":"2202", "Letters":"", "Transliteration":"", "Difficulty":"", "Notes":""},{"Id":"morning", "Kind":"Noun", "Category":"Time", "Form":"", "Article":"", "LinkedWord":"", "SunMoon":"", "Arabic":"صباح", "Symbols":"", "Drawing":"25", "Letters":"", "Transliteration":"", "Difficulty":"", "Notes":"added by stefano"},{"Id":"second", "Kind":"Noun", "Category":"Time", "Form":"", "Article":"", "LinkedWord":"", "SunMoon":"", "Arabic":"ثانية", "Symbols":"", "Drawing":"", "Letters":"ثـ ـا نـ ـيـ ـة", "Transliteration":"thaniya", "Difficulty":"", "Notes":""},{"Id":"spring", "Kind":"Noun", "Category":"Time", "Form":"", "Article":"", "LinkedWord":"", "SunMoon":"", "Arabic":"ربيع", "Symbols":"", "Drawing":"2192", "Letters":"", "Transliteration":"", "Difficulty":"", "Notes":""},{"Id":"winter", "Kind":"Noun", "Category":"Time", "Form":"", "Article":"", "LinkedWord":"", "SunMoon":"", "Arabic":"شتاء", "Symbols":"hamza", "Drawing":"BF", "Letters":"", "Transliteration":"", "Difficulty":"", "Notes":""},{"Id":"year", "Kind":"Noun", "Category":"Time", "Form":"", "Article":"", "LinkedWord":"", "SunMoon":"", "Arabic":"عام", "Symbols":"", "Drawing":"201C", "Letters":"عـ ـا م", "Transliteration":"a’am", "Difficulty":"", "Notes":""},{"Id":"bus", "Kind":"Noun", "Category":"Vehicle", "Form":"", "Article":"", "LinkedWord":"", "SunMoon":"", "Arabic":"باص", "Symbols":"", "Drawing":"44", "Letters":"", "Transliteration":"", "Difficulty":"", "Notes":""},{"Id":"the_bus", "Kind":"Noun", "Category":"Vehicle", "Form":"", "Article":"Determinative", "LinkedWord":"bus", "SunMoon":"", "Arabic":"الباص", "Symbols":"", "Drawing":"44", "Letters":"", "Transliteration":"", "Difficulty":"", "Notes":"moon"},{"Id":"hot_temperature", "Kind":"Adjective", "Category":"", "Form":"", "Article":"", "LinkedWord":"", "SunMoon":"", "Arabic":"سخن", "Symbols":"", "Drawing":"", "Letters":"سـ ـخـ ـن", "Transliteration":"sekhen", "Difficulty":"", "Notes":""},{"Id":"hot_weather", "Kind":"Adjective", "Category":"", "Form":"", "Article":"", "LinkedWord":"", "SunMoon":"", "Arabic":"شوب", "Symbols":"", "Drawing":"", "Letters":"شـ ـو ب", "Transliteration":"shob", "Difficulty":"1", "Notes":""},{"Id":"the_beautiful", "Kind":"Adjective", "Category":"", "Form":"", "Article":"Determinative", "LinkedWord":"beautiful", "SunMoon":"", "Arabic":"الجميل", "Symbols":"", "Drawing":"", "Letters":"", "Transliteration":"", "Difficulty":"", "Notes":""},{"Id":"hi", "Kind":"Adverb", "Category":"", "Form":"", "Article":"", "LinkedWord":"", "SunMoon":"", "Arabic":"مرحباً", "Symbols":"alef_fathah tanwin", "Drawing":"", "Letters":"", "Transliteration":"", "Difficulty":"", "Notes":""},{"Id":"of_course", "Kind":"Adverb", "Category":"", "Form":"", "Article":"", "LinkedWord":"", "SunMoon":"", "Arabic":"طبعاً", "Symbols":"alef_fathah_tanwin", "Drawing":"", "Letters":"", "Transliteration":"", "Difficulty":"", "Notes":""},{"Id":"sure", "Kind":"Adverb", "Category":"", "Form":"", "Article":"", "LinkedWord":"", "SunMoon":"", "Arabic":"عفواً", "Symbols":"alef_fathah_tanwin", "Drawing":"", "Letters":"", "Transliteration":"", "Difficulty":"", "Notes":""},{"Id":"thankyou", "Kind":"Adverb", "Category":"", "Form":"", "Article":"", "LinkedWord":"", "SunMoon":"", "Arabic":"شكراً", "Symbols":"alef_fathah_tanwin", "Drawing":"", "Letters":"", "Transliteration":"", "Difficulty":"", "Notes":""},{"Id":"welcome", "Kind":"Adverb", "Category":"", "Form":"", "Article":"", "LinkedWord":"", "SunMoon":"", "Arabic":"أهلاً", "Symbols":"alef_fathah_tanwin", "Drawing":"", "Letters":"", "Transliteration":"", "Difficulty":"", "Notes":""},{"Id":"al", "Kind":"Article", "Category":"", "Form":"", "Article":"", "LinkedWord":"", "SunMoon":"", "Arabic":"الـ", "Symbols":"", "Drawing":"", "Letters":"", "Transliteration":"al", "Difficulty":"", "Notes":"determinative - combination of alef & laam together"},{"Id":"knowledge", "Kind":"Noun", "Category":"", "Form":"", "Article":"", "LinkedWord":"", "SunMoon":"", "Arabic":"عِلْم", "Symbols":"ain_kasrah,lam_sukun", "Drawing":"5C", "Letters":"", "Transliteration":"", "Difficulty":"", "Notes":""},{"Id":"lentil", "Kind":"Noun", "Category":"", "Form":"", "Article":"", "LinkedWord":"", "SunMoon":"", "Arabic":"عدس", "Symbols":"", "Drawing":"29", "Letters":"", "Transliteration":"", "Difficulty":"", "Notes":""},{"Id":"light", "Kind":"Noun", "Category":"", "Form":"", "Article":"", "LinkedWord":"", "SunMoon":"", "Arabic":"ضوء", "Symbols":"", "Drawing":"B7", "Letters":"", "Transliteration":"", "Difficulty":"", "Notes":""},{"Id":"melancholy", "Kind":"Noun", "Category":"", "Form":"", "Article":"", "LinkedWord":"", "SunMoon":"", "Arabic":"كآبة", "Symbols":"alef_maddah", "Drawing":"BB", "Letters":"", "Transliteration":"", "Difficulty":"", "Notes":""},{"Id":"nest", "Kind":"Noun", "Category":"", "Form":"", "Article":"", "LinkedWord":"", "SunMoon":"", "Arabic":"عش", "Symbols":"", "Drawing":"DA", "Letters":"", "Transliteration":"", "Difficulty":"", "Notes":""},{"Id":"peace", "Kind":"Noun", "Category":"", "Form":"", "Article":"", "LinkedWord":"", "SunMoon":"", "Arabic":"سلام", "Symbols":"", "Drawing":"40", "Letters":"", "Transliteration":"", "Difficulty":"", "Notes":"added by stefano"},{"Id":"pearl", "Kind":"Noun", "Category":"", "Form":"", "Article":"", "LinkedWord":"", "SunMoon":"", "Arabic":"لؤلؤ", "Symbols":"waw_hamza", "Drawing":"E0", "Letters":"", "Transliteration":"", "Difficulty":"", "Notes":""},{"Id":"sound", "Kind":"Noun", "Category":"", "Form":"", "Article":"", "LinkedWord":"", "SunMoon":"", "Arabic":"صوت", "Symbols":"", "Drawing":"EC", "Letters":"", "Transliteration":"", "Difficulty":"", "Notes":""},{"Id":"the_light", "Kind":"Noun", "Category":"", "Form":"", "Article":"Determinative", "LinkedWord":"light", "SunMoon":"", "Arabic":"الضوء", "Symbols":"", "Drawing":"B7", "Letters":"", "Transliteration":"", "Difficulty":"", "Notes":"sun"},{"Id":"voice", "Kind":"Noun", "Category":"", "Form":"", "Article":"", "LinkedWord":"", "SunMoon":"", "Arabic":"صوت", "Symbols":"", "Drawing":"F9", "Letters":"", "Transliteration":"", "Difficulty":"", "Notes":""},{"Id":"with_article", "Kind":"UI", "Category":"", "Form":"", "Article":"", "LinkedWord":"", "SunMoon":"", "Arabic":"مع أداة التعريف", "Symbols":"", "Drawing":"", "Letters":"", "Transliteration":"", "Difficulty":"", "Notes":""},{"Id":"without_article", "Kind":"UI", "Category":"", "Form":"", "Article":"", "LinkedWord":"", "SunMoon":"", "Arabic":"دون أداة التعريف", "Symbols":"", "Drawing":"", "Letters":"", "Transliteration":"", "Difficulty":"", "Notes":""},{"Id":"singular", "Kind":"UI", "Category":"", "Form":"", "Article":"", "LinkedWord":"", "SunMoon":"", "Arabic":"مفرد", "Symbols":"", "Drawing":"", "Letters":"", "Transliteration":"", "Difficulty":"", "Notes":""},{"Id":"dual", "Kind":"UI", "Category":"", "Form":"", "Article":"", "LinkedWord":"", "SunMoon":"", "Arabic":"مثنى", "Symbols":"", "Drawing":"", "Letters":"", "Transliteration":"", "Difficulty":"", "Notes":""},{"Id":"plural", "Kind":"UI", "Category":"", "Form":"", "Article":"", "LinkedWord":"", "SunMoon":"", "Arabic":"جمع", "Symbols":"", "Drawing":"", "Letters":"", "Transliteration":"", "Difficulty":"", "Notes":""},{"Id":"vowel", "Kind":"UI", "Category":"", "Form":"", "Article":"", "LinkedWord":"", "SunMoon":"", "Arabic":"حرف علة", "Symbols":"", "Drawing":"", "Letters":"", "Transliteration":"", "Difficulty":"", "Notes":""},{"Id":"consonant", "Kind":"UI", "Category":"", "Form":"", "Article":"", "LinkedWord":"", "SunMoon":"", "Arabic":"حرف ساكن", "Symbols":"", "Drawing":"", "Letters":"", "Transliteration":"", "Difficulty":"", "Notes":""},{"Id":"agreed", "Kind":"Verb", "Category":"", "Form":"", "Article":"", "LinkedWord":"", "SunMoon":"", "Arabic":"وافَقَ", "Symbols":"feh_fathah,qaf_fathah", "Drawing":"", "Letters":"و ا فـَ ـقَ", "Transliteration":"wafaqa", "Difficulty":"", "Notes":""},{"Id":"ate", "Kind":"Verb", "Category":"", "Form":"", "Article":"", "LinkedWord":"", "SunMoon":"", "Arabic":"أَكَلَ", "Symbols":"alef_fathah,kaf_fathah,lam_fathah", "Drawing":"", "Letters":"أَ كـَ ـلَ ", "Transliteration":"akala", "Difficulty":"", "Notes":""},{"Id":"believed", "Kind":"Verb", "Category":"", "Form":"", "Article":"", "LinkedWord":"", "SunMoon":"", "Arabic":"آمَنَ", "Symbols":"alef_maddah,meem_fathah,noon_fathah", "Drawing":"", "Letters":"آ مـ ـن", "Transliteration":"aamana", "Difficulty":"", "Notes":""},{"Id":"carried", "Kind":"Verb", "Category":"", "Form":"", "Article":"", "LinkedWord":"", "SunMoon":"", "Arabic":"حَمَلَ", "Symbols":"hah_fathah,meem_fathah,lam_fathah", "Drawing":"", "Letters":"", "Transliteration":"", "Difficulty":"", "Notes":""},{"Id":"caught", "Kind":"Verb", "Category":"", "Form":"", "Article":"", "LinkedWord":"", "SunMoon":"", "Arabic":"مَسَكَ", "Symbols":"meem_fathah,seen_fathah,kaf_fathah", "Drawing":"", "Letters":"", "Transliteration":"", "Difficulty":"", "Notes":""},{"Id":"cried", "Kind":"Verb", "Category":"", "Form":"", "Article":"", "LinkedWord":"", "SunMoon":"", "Arabic":"بكى", "Symbols":"", "Drawing":"", "Letters":"", "Transliteration":"", "Difficulty":"", "Notes":""},{"Id":"drank", "Kind":"Verb", "Category":"", "Form":"", "Article":"", "LinkedWord":"", "SunMoon":"", "Arabic":"شَرِبَ", "Symbols":"sheen_fathah,reh_kasrah,beh_fathah", "Drawing":"", "Letters":"", "Transliteration":"", "Difficulty":"", "Notes":""},{"Id":"flapped", "Kind":"Verb", "Category":"", "Form":"", "Article":"", "LinkedWord":"", "SunMoon":"", "Arabic":"رَفْرَفَ", "Symbols":"reh_fathah,feh_sukun,reh_fathah,feh_fathah", "Drawing":"", "Letters":"", "Transliteration":"", "Difficulty":"", "Notes":""},{"Id":"flew", "Kind":"Verb", "Category":"", "Form":"", "Article":"", "LinkedWord":"", "SunMoon":"", "Arabic":"طار", "Symbols":"", "Drawing":"", "Letters":"", "Transliteration":"", "Difficulty":"", "Notes":""},{"Id":"laughed", "Kind":"Verb", "Category":"", "Form":"", "Article":"", "LinkedWord":"", "SunMoon":"", "Arabic":"ضَحِكَ", "Symbols":"dad_fathah,hah_kasrah,kaf_fathah", "Drawing":"", "Letters":"", "Transliteration":"", "Difficulty":"", "Notes":""},{"Id":"opened", "Kind":"Verb", "Category":"", "Form":"", "Article":"", "LinkedWord":"", "SunMoon":"", "Arabic":"فَتَحَ", "Symbols":"feh_fathah,teh_fathah,hah_fathah", "Drawing":"", "Letters":"", "Transliteration":"", "Difficulty":"", "Notes":""},{"Id":"played", "Kind":"Verb", "Category":"", "Form":"", "Article":"", "LinkedWord":"", "SunMoon":"", "Arabic":"لَعِبَ", "Symbols":"lam_fathah,ain_kasrah,beh_fathah", "Drawing":"", "Letters":"", "Transliteration":"", "Difficulty":"", "Notes":""},{"Id":"released", "Kind":"Verb", "Category":"", "Form":"", "Article":"", "LinkedWord":"", "SunMoon":"", "Arabic":"تَرَكَ", "Symbols":"teh_fathah,reh_fathah,kaf_fathah", "Drawing":"", "Letters":"", "Transliteration":"", "Difficulty":"", "Notes":""},{"Id":"sat", "Kind":"Verb", "Category":"", "Form":"", "Article":"", "LinkedWord":"", "SunMoon":"", "Arabic":"جَلَسَ", "Symbols":"jeem_fathah,lam_fathah,seen_fathah", "Drawing":"", "Letters":"", "Transliteration":"", "Difficulty":"", "Notes":""},{"Id":"saw", "Kind":"Verb", "Category":"", "Form":"", "Article":"", "LinkedWord":"", "SunMoon":"", "Arabic":"رأى", "Symbols":"", "Drawing":"", "Letters":"", "Transliteration":"", "Difficulty":"", "Notes":""},{"Id":"studied", "Kind":"Verb", "Category":"", "Form":"", "Article":"", "LinkedWord":"", "SunMoon":"", "Arabic":"دَرَسَ", "Symbols":"dal_fathah,reh_fathah,seen_fathah", "Drawing":"", "Letters":"", "Transliteration":"", "Difficulty":"", "Notes":""},{"Id":"understood", "Kind":"Verb", "Category":"", "Form":"", "Article":"", "LinkedWord":"", "SunMoon":"", "Arabic":"فَهِمَ", "Symbols":"feh_fathah,heh_kasrah,meem_fathah", "Drawing":"", "Letters":"", "Transliteration":"", "Difficulty":"", "Notes":""},{"Id":"walked", "Kind":"Verb", "Category":"", "Form":"", "Article":"", "LinkedWord":"", "SunMoon":"", "Arabic":"مشى", "Symbols":"", "Drawing":"", "Letters":"", "Transliteration":"", "Difficulty":"", "Notes":""},{"Id":"went", "Kind":"Verb", "Category":"", "Form":"", "Article":"", "LinkedWord":"", "SunMoon":"", "Arabic":"ذَهَبَ", "Symbols":"thal_fathah,heh_fathah,beh_fathah", "Drawing":"", "Letters":"", "Transliteration":"", "Difficulty":"", "Notes":""},{"Id":"won", "Kind":"Verb", "Category":"", "Form":"", "Article":"", "LinkedWord":"", "SunMoon":"", "Arabic":"رَبِحَ", "Symbols":"reh_fathah,beh_kasrah,hah_fathah", "Drawing":"", "Letters":"", "Transliteration":"", "Difficulty":"", "Notes":""},{"Id":"wore", "Kind":"Verb", "Category":"", "Form":"", "Article":"", "LinkedWord":"", "SunMoon":"", "Arabic":"لَبِسَ", "Symbols":"lam_fathah,beh_kasrah,seen_fathah", "Drawing":"", "Letters":"", "Transliteration":"", "Difficulty":"", "Notes":"double_diacritic"},{"Id":"wrote", "Kind":"Verb", "Category":"", "Form":"", "Article":"", "LinkedWord":"", "SunMoon":"", "Arabic":"كَتَبَ", "Symbols":"kaf_fathah,teh_fathah,beh_fathah", "Drawing":"", "Letters":"", "Transliteration":"", "Difficulty":"", "Notes":""}]