[{"Id":"AlphabetSong", "Status":"", "Parent":"", "Description":"video", "Team":"VGWB", "Title_En":"The Alphabet Song", "Variation":"", "Title_Ar":"أغنية الحروف", "Scene":"", "TitleNew":"The letters song"},{"Id":"Balloons_counting", "Status":"", "Parent":"Balloons_spelling", "Description":"", "Team":"Wixel", "Title_En":"Balloons", "Variation":"counting", "Title_Ar":"البالونات و الارقام", "Scene":"game_Balloons", "TitleNew":""},{"Id":"Balloons_letter", "Status":"", "Parent":"Balloons_spelling", "Description":"", "Team":"Wixel", "Title_En":"Balloons", "Variation":"letters", "Title_Ar":"البالونات و الحروف", "Scene":"game_Balloons", "TitleNew":""},{"Id":"Balloons_spelling", "Status":"dev", "Parent":"", "Description":"", "Team":"Wixel", "Title_En":"Balloons", "Variation":"spelling", "Title_Ar":"البالونات و التهجئة", "Scene":"game_Balloons", "TitleNew":""},{"Id":"Balloons_words", "Status":"", "Parent":"Balloons_spelling", "Description":"", "Team":"Wixel", "Title_En":"Balloons", "Variation":"words", "Title_Ar":"البالونات و الكلمات ", "Scene":"game_Balloons", "TitleNew":""},{"Id":"ColorTickle", "Status":"", "Parent":"", "Description":"", "Team":"Students", "Title_En":"Color Tickle", "Variation":"", "Title_Ar":"دغدغات ملونة ", "Scene":"", "TitleNew":""},{"Id":"DancingDots", "Status":"active", "Parent":"", "Description":"", "Team":"Wixel", "Title_En":"Dancing Dots", "Variation":"", "Title_Ar":"حلبة الرقص", "Scene":"game_DancingDots", "TitleNew":"Dancing Arena"},{"Id":"DontWakeUp", "Status":"standby", "Parent":"", "Description":"", "Team":"VGWB", "Title_En":"Don't Wake Up", "Variation":"", "Title_Ar":"لا توقظ عنتورة", "Scene":"", "TitleNew":""},{"Id":"Egg", "Status":"dev", "Parent":"", "Description":"", "Team":"VGWB", "Title_En":"The Egg", "Variation":"", "Title_Ar":"بيضة الحروف", "Scene":"", "TitleNew":""},{"Id":"FastCrowd_alphabet", "Status":"", "Parent":"FastCrowd_spelling", "Description":"", "Team":"VGWB", "Title_En":"Fast Crowd ", "Variation":"alphabet", "Title_Ar":"جماهير حروف الابجدية", "Scene":"game_FastCrowd", "TitleNew":""},{"Id":"FastCrowd_counting", "Status":"", "Parent":"FastCrowd_spelling", "Description":"", "Team":"VGWB", "Title_En":"Fast Crowd", "Variation":"counting", "Title_Ar":"جماهير الارقام", "Scene":"game_FastCrowd", "TitleNew":""},{"Id":"FastCrowd_letter", "Status":"", "Parent":"FastCrowd_spelling", "Description":"", "Team":"VGWB", "Title_En":"Fast Crowd", "Variation":"letters", "Title_Ar":"جماهير الحروف", "Scene":"game_FastCrowd", "TitleNew":""},{"Id":"FastCrowd_spelling", "Status":"active", "Parent":"", "Description":"", "Team":"VGWB", "Title_En":"Fast Crowd", "Variation":"spelling", "Title_Ar":"جماهير التهجئة", "Scene":"game_FastCrowd", "TitleNew":""},{"Id":"FastCrowd_words", "Status":"active", "Parent":"FastCrowd_spelling", "Description":"", "Team":"VGWB", "Title_En":"Fast Crowd", "Variation":"words", "Title_Ar":"جماهير الكلمات", "Scene":"game_FastCrowd", "TitleNew":""},{"Id":"HiddenSource", "Status":"", "Parent":"", "Description":"", "Team":"Wixel", "Title_En":"Hidden Source", "Variation":"", "Title_Ar":"خذني إلى المنزل", "Scene":"", "TitleNew":"Take me home"},{"Id":"HideSeek", "Status":"", "Parent":"", "Description":"", "Team":"Students", "Title_En":"Hide & Seek", "Variation":"", "Title_Ar":"الغميضة", "Scene":"", "TitleNew":""},{"Id":"MakeFriends", "Status":"active", "Parent":"", "Description":"", "Team":"Wixel", "Title_En":"Make Friends", "Variation":"", "Title_Ar":"شرارة الصداقة", "Scene":"game_MakeFriends", "TitleNew":"Friendship spark"},{"Id":"Maze", "Status":"active", "Parent":"", "Description":"", "Team":"Wixel", "Title_En":"Maze", "Variation":"", "Title_Ar":"متاهة الصاروخ", "Scene":"game_Maze", "TitleNew":"Missle maze"},{"Id":"MissingLetter", "Status":"", "Parent":"", "Description":"", "Team":"Students", "Title_En":"Missing Letters", "Variation":"", "Title_Ar":"", "Scene":"", "TitleNew":""},{"Id":"MissingLetter_phrases", "Status":"", "Parent":"MissingLetter", "Description":"", "Team":"Students", "Title_En":"Missing Letters", "Variation":"phrases", "Title_Ar":"", "Scene":"", "TitleNew":""},{"Id":"MixedLetters_alphabet", "Status":"", "Parent":"", "Description":"", "Team":"Wixel", "Title_En":"Mixed Letters", "Variation":"alphabet", "Title_Ar":"سلطة الحروف", "Scene":"", "TitleNew":"Letters Salad"},{"Id":"MixedLetters_spelling", "Status":"", "Parent":"MixedLetters_alphabet", "Description":"", "Team":"Wixel", "Title_En":"Mixed Letters", "Variation":"spelling", "Title_Ar":"سلطة الكلمات", "Scene":"", "TitleNew":"Words Salad"},{"Id":"SickLetter", "Status":"", "Parent":"", "Description":"", "Team":"Wixel", "Title_En":"Mysterious Guest", "Variation":"", "Title_Ar":"الضيف الغامض", "Scene":"", "TitleNew":""},{"Id":"ReadingGame", "Status":"", "Parent":"", "Description":"", "Team":"VGWB", "Title_En":"Reading Game", "Variation":"", "Title_Ar":"", "Scene":"", "TitleNew":""},{"Id":"Scanner", "Status":"", "Parent":"", "Description":"", "Team":"Wixel", "Title_En":"Scanner", "Variation":"", "Title_Ar":"فاحص الحروف الضوئي", "Scene":"", "TitleNew":""},{"Id":"Scanner_phrase", "Status":"", "Parent":"Scanner", "Description":"", "Team":"Wixel", "Title_En":"Scanner", "Variation":"phrases", "Title_Ar":"فاحص الكلمات الضوئي", "Scene":"", "TitleNew":""},{"Id":"ThrowBalls_letters", "Status":"active", "Parent":"", "Description":"", "Team":"Wixel", "Title_En":"Throw Balls", "Variation":"letters", "Title_Ar":"صيد الحروف", "Scene":"game_ThrowBalls", "TitleNew":"Letter hunt"},{"Id":"ThrowBalls_words", "Status":"", "Parent":"ThrowBalls_letters", "Description":"", "Team":"Wixel", "Title_En":"Throw Balls", "Variation":"words", "Title_Ar":"صيد الكلمات", "Scene":"game_ThrowBalls", "TitleNew":"Word hunt"},{"Id":"Tobogan_letters", "Status":"active", "Parent":"", "Description":"", "Team":"VGWB", "Title_En":"Tobogan", "Variation":"letters", "Title_Ar":"برج الحروف ", "Scene":"game_Tobogan", "TitleNew":"letter tower"},{"Id":"Tobogan_words", "Status":"", "Parent":"Tobogan_letters", "Description":"", "Team":"VGWB", "Title_En":"Tobogan", "Variation":"words", "Title_Ar":"برج الكلمات ", "Scene":"game_Tobogan", "TitleNew":"Word tower"}]